Workbook

Sheet Parameters
A1: Parameter | B1: Value | C1: Description | D1: Symbol
A2: Retirement Age | B2: 65 | C2: Age at which pension starts | D2: R
A3: Contribution Rate | B3: 0.1 | C3: Percentage of salary | D3: CR
A4: Expense Charge | B4: 0.03 | C4: Deduction from contribution | D4: c
A5: Investment Return | B5: 0.07 | C5: Long-term investment return p.a. | D5: i
A6: Dummy Accrual | B6: 90 | C6: Dummy accrual for intermediate valuation | D6: A_dummy
A7: Contingency Margin | B7: 0.2 | C7: For single accrual equation of value | D7: margin
A8: Accrued Target | B8: 0.8 | C8: 1 - margin | D8: acc_target
A9: Actual Accrual Rate | B9: 81.921586 | C9: Solved from Eq of Value=0.8 | D9: A
A10: Pension Increase Rate | B10: 0.029512891 | C10: Solved for 0 surplus | D10: b

Sheet Calculations
A1: Member ID | B1: Age | C1: Contrib C0 | D1: Salary Incr s | E1: Death Age d | F1: Salary S0 | G1: Term n | H1: End Age | I1: Final Salary | J1: Ratio geom | K1: PV Gross Contrib t=0 | L1: PV Net Contrib t=0 | M1: Accum Val End | N1: Dummy Pens | O1: PV Pens@65 (Dum) | P1: PV Pens@0 (Dum) | Q1: PV DeathLump@0 (Dum) | R1: PV AccumFund@0 | S1: Target Pens | T1: Total Dum PV@0 | U1: PV Incr Pens@65 | V1: PV Incr Pens@0 | W1: PV Fix Death@0 | X1: Total Target PV@0 | Y1: Annuity Factor
A2: 1 | B2: 54 | C2: 1370 | D2: 0.0334 | E2: 81 | F2: 13700 | G2: =MIN(65-B2, MAX(0, E2-B2)) | H2: =B2+G2 | I2: =F2*(1+D2)^G2 | J2: =(1+D2)/(1+Parameters!$B$5) | K2: =IF(G2>0, IF(ROUND(J2, 6)=1, G2 * C2 * (1+Parameters!$B$5)^-0.5, C2 * (1-J2^G2)/(1-J2) * (1+Parameters!$B$5)^-0.5), 0) | L2: =K2*(1-Parameters!$B$4) | M2: =L2*(1+Parameters!$B$5)^G2 | N2: =IF(E2>=65, (65-B2)*I2/Parameters!$B$6, 0) | O2: =IF(E2>65, (1-(1+Parameters!$B$5)^-(E2-65))/Parameters!$B$5, 0) | P2: =N2 * O2 * (1+Parameters!$B$5)^-(65-B2) | Q2: =IF(AND(E2>=66, E2<=69), 5*N2*(1+Parameters!$B$5)^-(E2-B2), 0) | R2: =IF(E2<=65, L2, 0) | S2: =N2 * (Parameters!$B$6 / Parameters!$B$9) | T2: =P2 + Q2 | U2: =IF(E2>65, (1-((1+Parameters!$B$10)/(1+Parameters!$B$5))^(E2-65))/(((1+Parameters!$B$5)/(1+Parameters!$B$10))-1), 0) | V2: =S2 * U2 * (1+Parameters!$B$5)^-(65-B2) | W2: =IF(AND(E2>=66, E2<=69), 5*S2*(1+Parameters!$B$5)^-(E2-B2), 0) | X2: =V2 + W2 + R2 | Y2: =IF(E2>=65, M2/S2, "")
A3: 2 | B3: 21 | C3: 2880 | D3: 0.0256 | E3: 87 | F3: 28800 | G3: =MIN(65-B3, MAX(0, E3-B3)) | H3: =B3+G3 | I3: =F3*(1+D3)^G3 | J3: =(1+D3)/(1+Parameters!$B$5) | K3: =IF(G3>0, IF(ROUND(J3, 6)=1, G3 * C3 * (1+Parameters!$B$5)^-0.5, C3 * (1-J3^G3)/(1-J3) * (1+Parameters!$B$5)^-0.5), 0) | L3: =K3*(1-Parameters!$B$4) | M3: =L3*(1+Parameters!$B$5)^G3 | N3: =IF(E3>=65, (65-B3)*I3/Parameters!$B$6, 0) | O3: =IF(E3>65, (1-(1+Parameters!$B$5)^-(E3-65))/Parameters!$B$5, 0) | P3: =N3 * O3 * (1+Parameters!$B$5)^-(65-B3) | Q3: =IF(AND(E3>=66, E3<=69), 5*N3*(1+Parameters!$B$5)^-(E3-B3), 0) | R3: =IF(E3<=65, L3, 0) | S3: =N3 * (Parameters!$B$6 / Parameters!$B$9) | T3: =P3 + Q3 | U3: =IF(E3>65, (1-((1+Parameters!$B$10)/(1+Parameters!$B$5))^(E3-65))/(((1+Parameters!$B$5)/(1+Parameters!$B$10))-1), 0) | V3: =S3 * U3 * (1+Parameters!$B$5)^-(65-B3) | W3: =IF(AND(E3>=66, E3<=69), 5*S3*(1+Parameters!$B$5)^-(E3-B3), 0) | X3: =V3 + W3 + R3 | Y3: =IF(E3>=65, M3/S3, "")
A4: 3 | B4: 28 | C4: 3930 | D4: 0.0536 | E4: 85 | F4: 39300 | G4: =MIN(65-B4, MAX(0, E4-B4)) | H4: =B4+G4 | I4: =F4*(1+D4)^G4 | J4: =(1+D4)/(1+Parameters!$B$5) | K4: =IF(G4>0, IF(ROUND(J4, 6)=1, G4 * C4 * (1+Parameters!$B$5)^-0.5, C4 * (1-J4^G4)/(1-J4) * (1+Parameters!$B$5)^-0.5), 0) | L4: =K4*(1-Parameters!$B$4) | M4: =L4*(1+Parameters!$B$5)^G4 | N4: =IF(E4>=65, (65-B4)*I4/Parameters!$B$6, 0) | O4: =IF(E4>65, (1-(1+Parameters!$B$5)^-(E4-65))/Parameters!$B$5, 0) | P4: =N4 * O4 * (1+Parameters!$B$5)^-(65-B4) | Q4: =IF(AND(E4>=66, E4<=69), 5*N4*(1+Parameters!$B$5)^-(E4-B4), 0) | R4: =IF(E4<=65, L4, 0) | S4: =N4 * (Parameters!$B$6 / Parameters!$B$9) | T4: =P4 + Q4 | U4: =IF(E4>65, (1-((1+Parameters!$B$10)/(1+Parameters!$B$5))^(E4-65))/(((1+Parameters!$B$5)/(1+Parameters!$B$10))-1), 0) | V4: =S4 * U4 * (1+Parameters!$B$5)^-(65-B4) | W4: =IF(AND(E4>=66, E4<=69), 5*S4*(1+Parameters!$B$5)^-(E4-B4), 0) | X4: =V4 + W4 + R4 | Y4: =IF(E4>=65, M4/S4, "")
A5: 4 | B5: 46 | C5: 5450 | D5: 0.0095 | E5: 77 | F5: 54500 | G5: =MIN(65-B5, MAX(0, E5-B5)) | H5: =B5+G5 | I5: =F5*(1+D5)^G5 | J5: =(1+D5)/(1+Parameters!$B$5) | K5: =IF(G5>0, IF(ROUND(J5, 6)=1, G5 * C5 * (1+Parameters!$B$5)^-0.5, C5 * (1-J5^G5)/(1-J5) * (1+Parameters!$B$5)^-0.5), 0) | L5: =K5*(1-Parameters!$B$4) | M5: =L5*(1+Parameters!$B$5)^G5 | N5: =IF(E5>=65, (65-B5)*I5/Parameters!$B$6, 0) | O5: =IF(E5>65, (1-(1+Parameters!$B$5)^-(E5-65))/Parameters!$B$5, 0) | P5: =N5 * O5 * (1+Parameters!$B$5)^-(65-B5) | Q5: =IF(AND(E5>=66, E5<=69), 5*N5*(1+Parameters!$B$5)^-(E5-B5), 0) | R5: =IF(E5<=65, L5, 0) | S5: =N5 * (Parameters!$B$6 / Parameters!$B$9) | T5: =P5 + Q5 | U5: =IF(E5>65, (1-((1+Parameters!$B$10)/(1+Parameters!$B$5))^(E5-65))/(((1+Parameters!$B$5)/(1+Parameters!$B$10))-1), 0) | V5: =S5 * U5 * (1+Parameters!$B$5)^-(65-B5) | W5: =IF(AND(E5>=66, E5<=69), 5*S5*(1+Parameters!$B$5)^-(E5-B5), 0) | X5: =V5 + W5 + R5 | Y5: =IF(E5>=65, M5/S5, "")
A6: 5 | B6: 21 | C6: 1580 | D6: 0.0134 | E6: 103 | F6: 15800 | G6: =MIN(65-B6, MAX(0, E6-B6)) | H6: =B6+G6 | I6: =F6*(1+D6)^G6 | J6: =(1+D6)/(1+Parameters!$B$5) | K6: =IF(G6>0, IF(ROUND(J6, 6)=1, G6 * C6 * (1+Parameters!$B$5)^-0.5, C6 * (1-J6^G6)/(1-J6) * (1+Parameters!$B$5)^-0.5), 0) | L6: =K6*(1-Parameters!$B$4) | M6: =L6*(1+Parameters!$B$5)^G6 | N6: =IF(E6>=65, (65-B6)*I6/Parameters!$B$6, 0) | O6: =IF(E6>65, (1-(1+Parameters!$B$5)^-(E6-65))/Parameters!$B$5, 0) | P6: =N6 * O6 * (1+Parameters!$B$5)^-(65-B6) | Q6: =IF(AND(E6>=66, E6<=69), 5*N6*(1+Parameters!$B$5)^-(E6-B6), 0) | R6: =IF(E6<=65, L6, 0) | S6: =N6 * (Parameters!$B$6 / Parameters!$B$9) | T6: =P6 + Q6 | U6: =IF(E6>65, (1-((1+Parameters!$B$10)/(1+Parameters!$B$5))^(E6-65))/(((1+Parameters!$B$5)/(1+Parameters!$B$10))-1), 0) | V6: =S6 * U6 * (1+Parameters!$B$5)^-(65-B6) | W6: =IF(AND(E6>=66, E6<=69), 5*S6*(1+Parameters!$B$5)^-(E6-B6), 0) | X6: =V6 + W6 + R6 | Y6: =IF(E6>=65, M6/S6, "")
A7: 6 | B7: 48 | C7: 8500 | D7: 0.0457 | E7: 87 | F7: 85000 | G7: =MIN(65-B7, MAX(0, E7-B7)) | H7: =B7+G7 | I7: =F7*(1+D7)^G7 | J7: =(1+D7)/(1+Parameters!$B$5) | K7: =IF(G7>0, IF(ROUND(J7, 6)=1, G7 * C7 * (1+Parameters!$B$5)^-0.5, C7 * (1-J7^G7)/(1-J7) * (1+Parameters!$B$5)^-0.5), 0) | L7: =K7*(1-Parameters!$B$4) | M7: =L7*(1+Parameters!$B$5)^G7 | N7: =IF(E7>=65, (65-B7)*I7/Parameters!$B$6, 0) | O7: =IF(E7>65, (1-(1+Parameters!$B$5)^-(E7-65))/Parameters!$B$5, 0) | P7: =N7 * O7 * (1+Parameters!$B$5)^-(65-B7) | Q7: =IF(AND(E7>=66, E7<=69), 5*N7*(1+Parameters!$B$5)^-(E7-B7), 0) | R7: =IF(E7<=65, L7, 0) | S7: =N7 * (Parameters!$B$6 / Parameters!$B$9) | T7: =P7 + Q7 | U7: =IF(E7>65, (1-((1+Parameters!$B$10)/(1+Parameters!$B$5))^(E7-65))/(((1+Parameters!$B$5)/(1+Parameters!$B$10))-1), 0) | V7: =S7 * U7 * (1+Parameters!$B$5)^-(65-B7) | W7: =IF(AND(E7>=66, E7<=69), 5*S7*(1+Parameters!$B$5)^-(E7-B7), 0) | X7: =V7 + W7 + R7 | Y7: =IF(E7>=65, M7/S7, "")
A8: 7 | B8: 58 | C8: 4030 | D8: 0.0262 | E8: 79 | F8: 40300 | G8: =MIN(65-B8, MAX(0, E8-B8)) | H8: =B8+G8 | I8: =F8*(1+D8)^G8 | J8: =(1+D8)/(1+Parameters!$B$5) | K8: =IF(G8>0, IF(ROUND(J8, 6)=1, G8 * C8 * (1+Parameters!$B$5)^-0.5, C8 * (1-J8^G8)/(1-J8) * (1+Parameters!$B$5)^-0.5), 0) | L8: =K8*(1-Parameters!$B$4) | M8: =L8*(1+Parameters!$B$5)^G8 | N8: =IF(E8>=65, (65-B8)*I8/Parameters!$B$6, 0) | O8: =IF(E8>65, (1-(1+Parameters!$B$5)^-(E8-65))/Parameters!$B$5, 0) | P8: =N8 * O8 * (1+Parameters!$B$5)^-(65-B8) | Q8: =IF(AND(E8>=66, E8<=69), 5*N8*(1+Parameters!$B$5)^-(E8-B8), 0) | R8: =IF(E8<=65, L8, 0) | S8: =N8 * (Parameters!$B$6 / Parameters!$B$9) | T8: =P8 + Q8 | U8: =IF(E8>65, (1-((1+Parameters!$B$10)/(1+Parameters!$B$5))^(E8-65))/(((1+Parameters!$B$5)/(1+Parameters!$B$10))-1), 0) | V8: =S8 * U8 * (1+Parameters!$B$5)^-(65-B8) | W8: =IF(AND(E8>=66, E8<=69), 5*S8*(1+Parameters!$B$5)^-(E8-B8), 0) | X8: =V8 + W8 + R8 | Y8: =IF(E8>=65, M8/S8, "")
A9: 8 | B9: 57 | C9: 8440 | D9: 0.0059 | E9: 79 | F9: 84400 | G9: =MIN(65-B9, MAX(0, E9-B9)) | H9: =B9+G9 | I9: =F9*(1+D9)^G9 | J9: =(1+D9)/(1+Parameters!$B$5) | K9: =IF(G9>0, IF(ROUND(J9, 6)=1, G9 * C9 * (1+Parameters!$B$5)^-0.5, C9 * (1-J9^G9)/(1-J9) * (1+Parameters!$B$5)^-0.5), 0) | L9: =K9*(1-Parameters!$B$4) | M9: =L9*(1+Parameters!$B$5)^G9 | N9: =IF(E9>=65, (65-B9)*I9/Parameters!$B$6, 0) | O9: =IF(E9>65, (1-(1+Parameters!$B$5)^-(E9-65))/Parameters!$B$5, 0) | P9: =N9 * O9 * (1+Parameters!$B$5)^-(65-B9) | Q9: =IF(AND(E9>=66, E9<=69), 5*N9*(1+Parameters!$B$5)^-(E9-B9), 0) | R9: =IF(E9<=65, L9, 0) | S9: =N9 * (Parameters!$B$6 / Parameters!$B$9) | T9: =P9 + Q9 | U9: =IF(E9>65, (1-((1+Parameters!$B$10)/(1+Parameters!$B$5))^(E9-65))/(((1+Parameters!$B$5)/(1+Parameters!$B$10))-1), 0) | V9: =S9 * U9 * (1+Parameters!$B$5)^-(65-B9) | W9: =IF(AND(E9>=66, E9<=69), 5*S9*(1+Parameters!$B$5)^-(E9-B9), 0) | X9: =V9 + W9 + R9 | Y9: =IF(E9>=65, M9/S9, "")
A10: 9 | B10: 29 | C10: 1260 | D10: 0.0105 | E10: 76 | F10: 12600 | G10: =MIN(65-B10, MAX(0, E10-B10)) | H10: =B10+G10 | I10: =F10*(1+D10)^G10 | J10: =(1+D10)/(1+Parameters!$B$5) | K10: =IF(G10>0, IF(ROUND(J10, 6)=1, G10 * C10 * (1+Parameters!$B$5)^-0.5, C10 * (1-J10^G10)/(1-J10) * (1+Parameters!$B$5)^-0.5), 0) | L10: =K10*(1-Parameters!$B$4) | M10: =L10*(1+Parameters!$B$5)^G10 | N10: =IF(E10>=65, (65-B10)*I10/Parameters!$B$6, 0) | O10: =IF(E10>65, (1-(1+Parameters!$B$5)^-(E10-65))/Parameters!$B$5, 0) | P10: =N10 * O10 * (1+Parameters!$B$5)^-(65-B10) | Q10: =IF(AND(E10>=66, E10<=69), 5*N10*(1+Parameters!$B$5)^-(E10-B10), 0) | R10: =IF(E10<=65, L10, 0) | S10: =N10 * (Parameters!$B$6 / Parameters!$B$9) | T10: =P10 + Q10 | U10: =IF(E10>65, (1-((1+Parameters!$B$10)/(1+Parameters!$B$5))^(E10-65))/(((1+Parameters!$B$5)/(1+Parameters!$B$10))-1), 0) | V10: =S10 * U10 * (1+Parameters!$B$5)^-(65-B10) | W10: =IF(AND(E10>=66, E10<=69), 5*S10*(1+Parameters!$B$5)^-(E10-B10), 0) | X10: =V10 + W10 + R10 | Y10: =IF(E10>=65, M10/S10, "")
A11: 10 | B11: 40 | C11: 3850 | D11: 0.0275 | E11: 67 | F11: 38500 | G11: =MIN(65-B11, MAX(0, E11-B11)) | H11: =B11+G11 | I11: =F11*(1+D11)^G11 | J11: =(1+D11)/(1+Parameters!$B$5) | K11: =IF(G11>0, IF(ROUND(J11, 6)=1, G11 * C11 * (1+Parameters!$B$5)^-0.5, C11 * (1-J11^G11)/(1-J11) * (1+Parameters!$B$5)^-0.5), 0) | L11: =K11*(1-Parameters!$B$4) | M11: =L11*(1+Parameters!$B$5)^G11 | N11: =IF(E11>=65, (65-B11)*I11/Parameters!$B$6, 0) | O11: =IF(E11>65, (1-(1+Parameters!$B$5)^-(E11-65))/Parameters!$B$5, 0) | P11: =N11 * O11 * (1+Parameters!$B$5)^-(65-B11) | Q11: =IF(AND(E11>=66, E11<=69), 5*N11*(1+Parameters!$B$5)^-(E11-B11), 0) | R11: =IF(E11<=65, L11, 0) | S11: =N11 * (Parameters!$B$6 / Parameters!$B$9) | T11: =P11 + Q11 | U11: =IF(E11>65, (1-((1+Parameters!$B$10)/(1+Parameters!$B$5))^(E11-65))/(((1+Parameters!$B$5)/(1+Parameters!$B$10))-1), 0) | V11: =S11 * U11 * (1+Parameters!$B$5)^-(65-B11) | W11: =IF(AND(E11>=66, E11<=69), 5*S11*(1+Parameters!$B$5)^-(E11-B11), 0) | X11: =V11 + W11 + R11 | Y11: =IF(E11>=65, M11/S11, "")
A12: 11 | B12: 48 | C12: 11570 | D12: 0.0373 | E12: 80 | F12: 115700 | G12: =MIN(65-B12, MAX(0, E12-B12)) | H12: =B12+G12 | I12: =F12*(1+D12)^G12 | J12: =(1+D12)/(1+Parameters!$B$5) | K12: =IF(G12>0, IF(ROUND(J12, 6)=1, G12 * C12 * (1+Parameters!$B$5)^-0.5, C12 * (1-J12^G12)/(1-J12) * (1+Parameters!$B$5)^-0.5), 0) | L12: =K12*(1-Parameters!$B$4) | M12: =L12*(1+Parameters!$B$5)^G12 | N12: =IF(E12>=65, (65-B12)*I12/Parameters!$B$6, 0) | O12: =IF(E12>65, (1-(1+Parameters!$B$5)^-(E12-65))/Parameters!$B$5, 0) | P12: =N12 * O12 * (1+Parameters!$B$5)^-(65-B12) | Q12: =IF(AND(E12>=66, E12<=69), 5*N12*(1+Parameters!$B$5)^-(E12-B12), 0) | R12: =IF(E12<=65, L12, 0) | S12: =N12 * (Parameters!$B$6 / Parameters!$B$9) | T12: =P12 + Q12 | U12: =IF(E12>65, (1-((1+Parameters!$B$10)/(1+Parameters!$B$5))^(E12-65))/(((1+Parameters!$B$5)/(1+Parameters!$B$10))-1), 0) | V12: =S12 * U12 * (1+Parameters!$B$5)^-(65-B12) | W12: =IF(AND(E12>=66, E12<=69), 5*S12*(1+Parameters!$B$5)^-(E12-B12), 0) | X12: =V12 + W12 + R12 | Y12: =IF(E12>=65, M12/S12, "")
A13: 12 | B13: 41 | C13: 1040 | D13: 0.0431 | E13: 91 | F13: 10400 | G13: =MIN(65-B13, MAX(0, E13-B13)) | H13: =B13+G13 | I13: =F13*(1+D13)^G13 | J13: =(1+D13)/(1+Parameters!$B$5) | K13: =IF(G13>0, IF(ROUND(J13, 6)=1, G13 * C13 * (1+Parameters!$B$5)^-0.5, C13 * (1-J13^G13)/(1-J13) * (1+Parameters!$B$5)^-0.5), 0) | L13: =K13*(1-Parameters!$B$4) | M13: =L13*(1+Parameters!$B$5)^G13 | N13: =IF(E13>=65, (65-B13)*I13/Parameters!$B$6, 0) | O13: =IF(E13>65, (1-(1+Parameters!$B$5)^-(E13-65))/Parameters!$B$5, 0) | P13: =N13 * O13 * (1+Parameters!$B$5)^-(65-B13) | Q13: =IF(AND(E13>=66, E13<=69), 5*N13*(1+Parameters!$B$5)^-(E13-B13), 0) | R13: =IF(E13<=65, L13, 0) | S13: =N13 * (Parameters!$B$6 / Parameters!$B$9) | T13: =P13 + Q13 | U13: =IF(E13>65, (1-((1+Parameters!$B$10)/(1+Parameters!$B$5))^(E13-65))/(((1+Parameters!$B$5)/(1+Parameters!$B$10))-1), 0) | V13: =S13 * U13 * (1+Parameters!$B$5)^-(65-B13) | W13: =IF(AND(E13>=66, E13<=69), 5*S13*(1+Parameters!$B$5)^-(E13-B13), 0) | X13: =V13 + W13 + R13 | Y13: =IF(E13>=65, M13/S13, "")
... A251: 250 | B251: 44 | C251: 3980 | D251: 0.0191 | E251: 89 | F251: 39800 | G251: =MIN(65-B251, MAX(0, E251-B251)) | H251: =B251+G251 | I251: =F251*(1+D251)^G251 | J251: =(1+D251)/(1+Parameters!$B$5) | K251: =IF(G251>0, IF(ROUND(J251, 6)=1, G251 * C251 * (1+Parameters!$B$5)^-0.5, C251 * (1-J251^G251)/(1-J251) * (1+Parameters!$B$5)^-0.5), 0) | L251: =K251*(1-Parameters!$B$4) | M251: =L251*(1+Parameters!$B$5)^G251 | N251: =IF(E251>=65, (65-B251)*I251/Parameters!$B$6, 0) | O251: =IF(E251>65, (1-(1+Parameters!$B$5)^-(E251-65))/Parameters!$B$5, 0) | P251: =N251 * O251 * (1+Parameters!$B$5)^-(65-B251) | Q251: =IF(AND(E251>=66, E251<=69), 5*N251*(1+Parameters!$B$5)^-(E251-B251), 0) | R251: =IF(E251<=65, L251, 0) | S251: =N251 * (Parameters!$B$6 / Parameters!$B$9) | T251: =P251 + Q251 | U251: =IF(E251>65, (1-((1+Parameters!$B$10)/(1+Parameters!$B$5))^(E251-65))/(((1+Parameters!$B$5)/(1+Parameters!$B$10))-1), 0) | V251: =S251 * U251 * (1+Parameters!$B$5)^-(65-B251) | W251: =IF(AND(E251>=66, E251<=69), 5*S251*(1+Parameters!$B$5)^-(E251-B251), 0) | X251: =V251 + W251 + R251 | Y251: =IF(E251>=65, M251/S251, "")

Sheet Summary by Age
A1: Age | B1: Count | C1: Avg Contrib | D1: Min Contrib | E1: Max Contrib | F1: Avg Sal Incr | G1: Min Sal Incr | H1: Max Sal Incr | I1: Avg Death Age | J1: Min Death Age | K1: Max Death Age | L1: Avg Annuity Factor | M1: Min Annuity Factor | N1: Max Annuity Factor
A2: 18 | B2: =COUNTIFS(Calculations!$B:$B, A2) | C2: =IF(B2>0, AVERAGEIFS(Calculations!$C:$C, Calculations!$B:$B, A2), "") | D2: =IF(B2>0, MINIFS(Calculations!$C:$C, Calculations!$B:$B, A2), "") | E2: =IF(B2>0, MAXIFS(Calculations!$C:$C, Calculations!$B:$B, A2), "") | F2: =IF(B2>0, AVERAGEIFS(Calculations!$D:$D, Calculations!$B:$B, A2), "") | G2: =IF(B2>0, MINIFS(Calculations!$D:$D, Calculations!$B:$B, A2), "") | H2: =IF(B2>0, MAXIFS(Calculations!$D:$D, Calculations!$B:$B, A2), "") | I2: =IF(B2>0, AVERAGEIFS(Calculations!$E:$E, Calculations!$B:$B, A2), "") | J2: =IF(B2>0, MINIFS(Calculations!$E:$E, Calculations!$B:$B, A2), "") | K2: =IF(B2>0, MAXIFS(Calculations!$E:$E, Calculations!$B:$B, A2), "") | L2: =IF(COUNTIFS(Calculations!$B:$B, A2, Calculations!$E:$E, ">=65")>0, AVERAGEIFS(Calculations!$Y:$Y, Calculations!$B:$B, A2, Calculations!$E:$E, ">=65"), "") | M2: =IF(COUNTIFS(Calculations!$B:$B, A2, Calculations!$E:$E, ">=65")>0, MINIFS(Calculations!$Y:$Y, Calculations!$B:$B, A2, Calculations!$E:$E, ">=65"), "") | N2: =IF(COUNTIFS(Calculations!$B:$B, A2, Calculations!$E:$E, ">=65")>0, MAXIFS(Calculations!$Y:$Y, Calculations!$B:$B, A2, Calculations!$E:$E, ">=65"), "")
A3: 19 | B3: =COUNTIFS(Calculations!$B:$B, A3) | C3: =IF(B3>0, AVERAGEIFS(Calculations!$C:$C, Calculations!$B:$B, A3), "") | D3: =IF(B3>0, MINIFS(Calculations!$C:$C, Calculations!$B:$B, A3), "") | E3: =IF(B3>0, MAXIFS(Calculations!$C:$C, Calculations!$B:$B, A3), "") | F3: =IF(B3>0, AVERAGEIFS(Calculations!$D:$D, Calculations!$B:$B, A3), "") | G3: =IF(B3>0, MINIFS(Calculations!$D:$D, Calculations!$B:$B, A3), "") | H3: =IF(B3>0, MAXIFS(Calculations!$D:$D, Calculations!$B:$B, A3), "") | I3: =IF(B3>0, AVERAGEIFS(Calculations!$E:$E, Calculations!$B:$B, A3), "") | J3: =IF(B3>0, MINIFS(Calculations!$E:$E, Calculations!$B:$B, A3), "") | K3: =IF(B3>0, MAXIFS(Calculations!$E:$E, Calculations!$B:$B, A3), "") | L3: =IF(COUNTIFS(Calculations!$B:$B, A3, Calculations!$E:$E, ">=65")>0, AVERAGEIFS(Calculations!$Y:$Y, Calculations!$B:$B, A3, Calculations!$E:$E, ">=65"), "") | M3: =IF(COUNTIFS(Calculations!$B:$B, A3, Calculations!$E:$E, ">=65")>0, MINIFS(Calculations!$Y:$Y, Calculations!$B:$B, A3, Calculations!$E:$E, ">=65"), "") | N3: =IF(COUNTIFS(Calculations!$B:$B, A3, Calculations!$E:$E, ">=65")>0, MAXIFS(Calculations!$Y:$Y, Calculations!$B:$B, A3, Calculations!$E:$E, ">=65"), "")
A4: 20 | B4: =COUNTIFS(Calculations!$B:$B, A4) | C4: =IF(B4>0, AVERAGEIFS(Calculations!$C:$C, Calculations!$B:$B, A4), "") | D4: =IF(B4>0, MINIFS(Calculations!$C:$C, Calculations!$B:$B, A4), "") | E4: =IF(B4>0, MAXIFS(Calculations!$C:$C, Calculations!$B:$B, A4), "") | F4: =IF(B4>0, AVERAGEIFS(Calculations!$D:$D, Calculations!$B:$B, A4), "") | G4: =IF(B4>0, MINIFS(Calculations!$D:$D, Calculations!$B:$B, A4), "") | H4: =IF(B4>0, MAXIFS(Calculations!$D:$D, Calculations!$B:$B, A4), "") | I4: =IF(B4>0, AVERAGEIFS(Calculations!$E:$E, Calculations!$B:$B, A4), "") | J4: =IF(B4>0, MINIFS(Calculations!$E:$E, Calculations!$B:$B, A4), "") | K4: =IF(B4>0, MAXIFS(Calculations!$E:$E, Calculations!$B:$B, A4), "") | L4: =IF(COUNTIFS(Calculations!$B:$B, A4, Calculations!$E:$E, ">=65")>0, AVERAGEIFS(Calculations!$Y:$Y, Calculations!$B:$B, A4, Calculations!$E:$E, ">=65"), "") | M4: =IF(COUNTIFS(Calculations!$B:$B, A4, Calculations!$E:$E, ">=65")>0, MINIFS(Calculations!$Y:$Y, Calculations!$B:$B, A4, Calculations!$E:$E, ">=65"), "") | N4: =IF(COUNTIFS(Calculations!$B:$B, A4, Calculations!$E:$E, ">=65")>0, MAXIFS(Calculations!$Y:$Y, Calculations!$B:$B, A4, Calculations!$E:$E, ">=65"), "")
A5: 21 | B5: =COUNTIFS(Calculations!$B:$B, A5) | C5: =IF(B5>0, AVERAGEIFS(Calculations!$C:$C, Calculations!$B:$B, A5), "") | D5: =IF(B5>0, MINIFS(Calculations!$C:$C, Calculations!$B:$B, A5), "") | E5: =IF(B5>0, MAXIFS(Calculations!$C:$C, Calculations!$B:$B, A5), "") | F5: =IF(B5>0, AVERAGEIFS(Calculations!$D:$D, Calculations!$B:$B, A5), "") | G5: =IF(B5>0, MINIFS(Calculations!$D:$D, Calculations!$B:$B, A5), "") | H5: =IF(B5>0, MAXIFS(Calculations!$D:$D, Calculations!$B:$B, A5), "") | I5: =IF(B5>0, AVERAGEIFS(Calculations!$E:$E, Calculations!$B:$B, A5), "") | J5: =IF(B5>0, MINIFS(Calculations!$E:$E, Calculations!$B:$B, A5), "") | K5: =IF(B5>0, MAXIFS(Calculations!$E:$E, Calculations!$B:$B, A5), "") | L5: =IF(COUNTIFS(Calculations!$B:$B, A5, Calculations!$E:$E, ">=65")>0, AVERAGEIFS(Calculations!$Y:$Y, Calculations!$B:$B, A5, Calculations!$E:$E, ">=65"), "") | M5: =IF(COUNTIFS(Calculations!$B:$B, A5, Calculations!$E:$E, ">=65")>0, MINIFS(Calculations!$Y:$Y, Calculations!$B:$B, A5, Calculations!$E:$E, ">=65"), "") | N5: =IF(COUNTIFS(Calculations!$B:$B, A5, Calculations!$E:$E, ">=65")>0, MAXIFS(Calculations!$Y:$Y, Calculations!$B:$B, A5, Calculations!$E:$E, ">=65"), "")
A6: 22 | B6: =COUNTIFS(Calculations!$B:$B, A6) | C6: =IF(B6>0, AVERAGEIFS(Calculations!$C:$C, Calculations!$B:$B, A6), "") | D6: =IF(B6>0, MINIFS(Calculations!$C:$C, Calculations!$B:$B, A6), "") | E6: =IF(B6>0, MAXIFS(Calculations!$C:$C, Calculations!$B:$B, A6), "") | F6: =IF(B6>0, AVERAGEIFS(Calculations!$D:$D, Calculations!$B:$B, A6), "") | G6: =IF(B6>0, MINIFS(Calculations!$D:$D, Calculations!$B:$B, A6), "") | H6: =IF(B6>0, MAXIFS(Calculations!$D:$D, Calculations!$B:$B, A6), "") | I6: =IF(B6>0, AVERAGEIFS(Calculations!$E:$E, Calculations!$B:$B, A6), "") | J6: =IF(B6>0, MINIFS(Calculations!$E:$E, Calculations!$B:$B, A6), "") | K6: =IF(B6>0, MAXIFS(Calculations!$E:$E, Calculations!$B:$B, A6), "") | L6: =IF(COUNTIFS(Calculations!$B:$B, A6, Calculations!$E:$E, ">=65")>0, AVERAGEIFS(Calculations!$Y:$Y, Calculations!$B:$B, A6, Calculations!$E:$E, ">=65"), "") | M6: =IF(COUNTIFS(Calculations!$B:$B, A6, Calculations!$E:$E, ">=65")>0, MINIFS(Calculations!$Y:$Y, Calculations!$B:$B, A6, Calculations!$E:$E, ">=65"), "") | N6: =IF(COUNTIFS(Calculations!$B:$B, A6, Calculations!$E:$E, ">=65")>0, MAXIFS(Calculations!$Y:$Y, Calculations!$B:$B, A6, Calculations!$E:$E, ">=65"), "")
A7: 23 | B7: =COUNTIFS(Calculations!$B:$B, A7) | C7: =IF(B7>0, AVERAGEIFS(Calculations!$C:$C, Calculations!$B:$B, A7), "") | D7: =IF(B7>0, MINIFS(Calculations!$C:$C, Calculations!$B:$B, A7), "") | E7: =IF(B7>0, MAXIFS(Calculations!$C:$C, Calculations!$B:$B, A7), "") | F7: =IF(B7>0, AVERAGEIFS(Calculations!$D:$D, Calculations!$B:$B, A7), "") | G7: =IF(B7>0, MINIFS(Calculations!$D:$D, Calculations!$B:$B, A7), "") | H7: =IF(B7>0, MAXIFS(Calculations!$D:$D, Calculations!$B:$B, A7), "") | I7: =IF(B7>0, AVERAGEIFS(Calculations!$E:$E, Calculations!$B:$B, A7), "") | J7: =IF(B7>0, MINIFS(Calculations!$E:$E, Calculations!$B:$B, A7), "") | K7: =IF(B7>0, MAXIFS(Calculations!$E:$E, Calculations!$B:$B, A7), "") | L7: =IF(COUNTIFS(Calculations!$B:$B, A7, Calculations!$E:$E, ">=65")>0, AVERAGEIFS(Calculations!$Y:$Y, Calculations!$B:$B, A7, Calculations!$E:$E, ">=65"), "") | M7: =IF(COUNTIFS(Calculations!$B:$B, A7, Calculations!$E:$E, ">=65")>0, MINIFS(Calculations!$Y:$Y, Calculations!$B:$B, A7, Calculations!$E:$E, ">=65"), "") | N7: =IF(COUNTIFS(Calculations!$B:$B, A7, Calculations!$E:$E, ">=65")>0, MAXIFS(Calculations!$Y:$Y, Calculations!$B:$B, A7, Calculations!$E:$E, ">=65"), "")
A8: 24 | B8: =COUNTIFS(Calculations!$B:$B, A8) | C8: =IF(B8>0, AVERAGEIFS(Calculations!$C:$C, Calculations!$B:$B, A8), "") | D8: =IF(B8>0, MINIFS(Calculations!$C:$C, Calculations!$B:$B, A8), "") | E8: =IF(B8>0, MAXIFS(Calculations!$C:$C, Calculations!$B:$B, A8), "") | F8: =IF(B8>0, AVERAGEIFS(Calculations!$D:$D, Calculations!$B:$B, A8), "") | G8: =IF(B8>0, MINIFS(Calculations!$D:$D, Calculations!$B:$B, A8), "") | H8: =IF(B8>0, MAXIFS(Calculations!$D:$D, Calculations!$B:$B, A8), "") | I8: =IF(B8>0, AVERAGEIFS(Calculations!$E:$E, Calculations!$B:$B, A8), "") | J8: =IF(B8>0, MINIFS(Calculations!$E:$E, Calculations!$B:$B, A8), "") | K8: =IF(B8>0, MAXIFS(Calculations!$E:$E, Calculations!$B:$B, A8), "") | L8: =IF(COUNTIFS(Calculations!$B:$B, A8, Calculations!$E:$E, ">=65")>0, AVERAGEIFS(Calculations!$Y:$Y, Calculations!$B:$B, A8, Calculations!$E:$E, ">=65"), "") | M8: =IF(COUNTIFS(Calculations!$B:$B, A8, Calculations!$E:$E, ">=65")>0, MINIFS(Calculations!$Y:$Y, Calculations!$B:$B, A8, Calculations!$E:$E, ">=65"), "") | N8: =IF(COUNTIFS(Calculations!$B:$B, A8, Calculations!$E:$E, ">=65")>0, MAXIFS(Calculations!$Y:$Y, Calculations!$B:$B, A8, Calculations!$E:$E, ">=65"), "")
A9: 25 | B9: =COUNTIFS(Calculations!$B:$B, A9) | C9: =IF(B9>0, AVERAGEIFS(Calculations!$C:$C, Calculations!$B:$B, A9), "") | D9: =IF(B9>0, MINIFS(Calculations!$C:$C, Calculations!$B:$B, A9), "") | E9: =IF(B9>0, MAXIFS(Calculations!$C:$C, Calculations!$B:$B, A9), "") | F9: =IF(B9>0, AVERAGEIFS(Calculations!$D:$D, Calculations!$B:$B, A9), "") | G9: =IF(B9>0, MINIFS(Calculations!$D:$D, Calculations!$B:$B, A9), "") | H9: =IF(B9>0, MAXIFS(Calculations!$D:$D, Calculations!$B:$B, A9), "") | I9: =IF(B9>0, AVERAGEIFS(Calculations!$E:$E, Calculations!$B:$B, A9), "") | J9: =IF(B9>0, MINIFS(Calculations!$E:$E, Calculations!$B:$B, A9), "") | K9: =IF(B9>0, MAXIFS(Calculations!$E:$E, Calculations!$B:$B, A9), "") | L9: =IF(COUNTIFS(Calculations!$B:$B, A9, Calculations!$E:$E, ">=65")>0, AVERAGEIFS(Calculations!$Y:$Y, Calculations!$B:$B, A9, Calculations!$E:$E, ">=65"), "") | M9: =IF(COUNTIFS(Calculations!$B:$B, A9, Calculations!$E:$E, ">=65")>0, MINIFS(Calculations!$Y:$Y, Calculations!$B:$B, A9, Calculations!$E:$E, ">=65"), "") | N9: =IF(COUNTIFS(Calculations!$B:$B, A9, Calculations!$E:$E, ">=65")>0, MAXIFS(Calculations!$Y:$Y, Calculations!$B:$B, A9, Calculations!$E:$E, ">=65"), "")
A10: 26 | B10: =COUNTIFS(Calculations!$B:$B, A10) | C10: =IF(B10>0, AVERAGEIFS(Calculations!$C:$C, Calculations!$B:$B, A10), "") | D10: =IF(B10>0, MINIFS(Calculations!$C:$C, Calculations!$B:$B, A10), "") | E10: =IF(B10>0, MAXIFS(Calculations!$C:$C, Calculations!$B:$B, A10), "") | F10: =IF(B10>0, AVERAGEIFS(Calculations!$D:$D, Calculations!$B:$B, A10), "") | G10: =IF(B10>0, MINIFS(Calculations!$D:$D, Calculations!$B:$B, A10), "") | H10: =IF(B10>0, MAXIFS(Calculations!$D:$D, Calculations!$B:$B, A10), "") | I10: =IF(B10>0, AVERAGEIFS(Calculations!$E:$E, Calculations!$B:$B, A10), "") | J10: =IF(B10>0, MINIFS(Calculations!$E:$E, Calculations!$B:$B, A10), "") | K10: =IF(B10>0, MAXIFS(Calculations!$E:$E, Calculations!$B:$B, A10), "") | L10: =IF(COUNTIFS(Calculations!$B:$B, A10, Calculations!$E:$E, ">=65")>0, AVERAGEIFS(Calculations!$Y:$Y, Calculations!$B:$B, A10, Calculations!$E:$E, ">=65"), "") | M10: =IF(COUNTIFS(Calculations!$B:$B, A10, Calculations!$E:$E, ">=65")>0, MINIFS(Calculations!$Y:$Y, Calculations!$B:$B, A10, Calculations!$E:$E, ">=65"), "") | N10: =IF(COUNTIFS(Calculations!$B:$B, A10, Calculations!$E:$E, ">=65")>0, MAXIFS(Calculations!$Y:$Y, Calculations!$B:$B, A10, Calculations!$E:$E, ">=65"), "")
A11: 27 | B11: =COUNTIFS(Calculations!$B:$B, A11) | C11: =IF(B11>0, AVERAGEIFS(Calculations!$C:$C, Calculations!$B:$B, A11), "") | D11: =IF(B11>0, MINIFS(Calculations!$C:$C, Calculations!$B:$B, A11), "") | E11: =IF(B11>0, MAXIFS(Calculations!$C:$C, Calculations!$B:$B, A11), "") | F11: =IF(B11>0, AVERAGEIFS(Calculations!$D:$D, Calculations!$B:$B, A11), "") | G11: =IF(B11>0, MINIFS(Calculations!$D:$D, Calculations!$B:$B, A11), "") | H11: =IF(B11>0, MAXIFS(Calculations!$D:$D, Calculations!$B:$B, A11), "") | I11: =IF(B11>0, AVERAGEIFS(Calculations!$E:$E, Calculations!$B:$B, A11), "") | J11: =IF(B11>0, MINIFS(Calculations!$E:$E, Calculations!$B:$B, A11), "") | K11: =IF(B11>0, MAXIFS(Calculations!$E:$E, Calculations!$B:$B, A11), "") | L11: =IF(COUNTIFS(Calculations!$B:$B, A11, Calculations!$E:$E, ">=65")>0, AVERAGEIFS(Calculations!$Y:$Y, Calculations!$B:$B, A11, Calculations!$E:$E, ">=65"), "") | M11: =IF(COUNTIFS(Calculations!$B:$B, A11, Calculations!$E:$E, ">=65")>0, MINIFS(Calculations!$Y:$Y, Calculations!$B:$B, A11, Calculations!$E:$E, ">=65"), "") | N11: =IF(COUNTIFS(Calculations!$B:$B, A11, Calculations!$E:$E, ">=65")>0, MAXIFS(Calculations!$Y:$Y, Calculations!$B:$B, A11, Calculations!$E:$E, ">=65"), "")
A12: 28 | B12: =COUNTIFS(Calculations!$B:$B, A12) | C12: =IF(B12>0, AVERAGEIFS(Calculations!$C:$C, Calculations!$B:$B, A12), "") | D12: =IF(B12>0, MINIFS(Calculations!$C:$C, Calculations!$B:$B, A12), "") | E12: =IF(B12>0, MAXIFS(Calculations!$C:$C, Calculations!$B:$B, A12), "") | F12: =IF(B12>0, AVERAGEIFS(Calculations!$D:$D, Calculations!$B:$B, A12), "") | G12: =IF(B12>0, MINIFS(Calculations!$D:$D, Calculations!$B:$B, A12), "") | H12: =IF(B12>0, MAXIFS(Calculations!$D:$D, Calculations!$B:$B, A12), "") | I12: =IF(B12>0, AVERAGEIFS(Calculations!$E:$E, Calculations!$B:$B, A12), "") | J12: =IF(B12>0, MINIFS(Calculations!$E:$E, Calculations!$B:$B, A12), "") | K12: =IF(B12>0, MAXIFS(Calculations!$E:$E, Calculations!$B:$B, A12), "") | L12: =IF(COUNTIFS(Calculations!$B:$B, A12, Calculations!$E:$E, ">=65")>0, AVERAGEIFS(Calculations!$Y:$Y, Calculations!$B:$B, A12, Calculations!$E:$E, ">=65"), "") | M12: =IF(COUNTIFS(Calculations!$B:$B, A12, Calculations!$E:$E, ">=65")>0, MINIFS(Calculations!$Y:$Y, Calculations!$B:$B, A12, Calculations!$E:$E, ">=65"), "") | N12: =IF(COUNTIFS(Calculations!$B:$B, A12, Calculations!$E:$E, ">=65")>0, MAXIFS(Calculations!$Y:$Y, Calculations!$B:$B, A12, Calculations!$E:$E, ">=65"), "")
A13: 29 | B13: =COUNTIFS(Calculations!$B:$B, A13) | C13: =IF(B13>0, AVERAGEIFS(Calculations!$C:$C, Calculations!$B:$B, A13), "") | D13: =IF(B13>0, MINIFS(Calculations!$C:$C, Calculations!$B:$B, A13), "") | E13: =IF(B13>0, MAXIFS(Calculations!$C:$C, Calculations!$B:$B, A13), "") | F13: =IF(B13>0, AVERAGEIFS(Calculations!$D:$D, Calculations!$B:$B, A13), "") | G13: =IF(B13>0, MINIFS(Calculations!$D:$D, Calculations!$B:$B, A13), "") | H13: =IF(B13>0, MAXIFS(Calculations!$D:$D, Calculations!$B:$B, A13), "") | I13: =IF(B13>0, AVERAGEIFS(Calculations!$E:$E, Calculations!$B:$B, A13), "") | J13: =IF(B13>0, MINIFS(Calculations!$E:$E, Calculations!$B:$B, A13), "") | K13: =IF(B13>0, MAXIFS(Calculations!$E:$E, Calculations!$B:$B, A13), "") | L13: =IF(COUNTIFS(Calculations!$B:$B, A13, Calculations!$E:$E, ">=65")>0, AVERAGEIFS(Calculations!$Y:$Y, Calculations!$B:$B, A13, Calculations!$E:$E, ">=65"), "") | M13: =IF(COUNTIFS(Calculations!$B:$B, A13, Calculations!$E:$E, ">=65")>0, MINIFS(Calculations!$Y:$Y, Calculations!$B:$B, A13, Calculations!$E:$E, ">=65"), "") | N13: =IF(COUNTIFS(Calculations!$B:$B, A13, Calculations!$E:$E, ">=65")>0, MAXIFS(Calculations!$Y:$Y, Calculations!$B:$B, A13, Calculations!$E:$E, ">=65"), "")
... A44: 60 | B44: =COUNTIFS(Calculations!$B:$B, A44) | C44: =IF(B44>0, AVERAGEIFS(Calculations!$C:$C, Calculations!$B:$B, A44), "") | D44: =IF(B44>0, MINIFS(Calculations!$C:$C, Calculations!$B:$B, A44), "") | E44: =IF(B44>0, MAXIFS(Calculations!$C:$C, Calculations!$B:$B, A44), "") | F44: =IF(B44>0, AVERAGEIFS(Calculations!$D:$D, Calculations!$B:$B, A44), "") | G44: =IF(B44>0, MINIFS(Calculations!$D:$D, Calculations!$B:$B, A44), "") | H44: =IF(B44>0, MAXIFS(Calculations!$D:$D, Calculations!$B:$B, A44), "") | I44: =IF(B44>0, AVERAGEIFS(Calculations!$E:$E, Calculations!$B:$B, A44), "") | J44: =IF(B44>0, MINIFS(Calculations!$E:$E, Calculations!$B:$B, A44), "") | K44: =IF(B44>0, MAXIFS(Calculations!$E:$E, Calculations!$B:$B, A44), "") | L44: =IF(COUNTIFS(Calculations!$B:$B, A44, Calculations!$E:$E, ">=65")>0, AVERAGEIFS(Calculations!$Y:$Y, Calculations!$B:$B, A44, Calculations!$E:$E, ">=65"), "") | M44: =IF(COUNTIFS(Calculations!$B:$B, A44, Calculations!$E:$E, ">=65")>0, MINIFS(Calculations!$Y:$Y, Calculations!$B:$B, A44, Calculations!$E:$E, ">=65"), "") | N44: =IF(COUNTIFS(Calculations!$B:$B, A44, Calculations!$E:$E, ">=65")>0, MAXIFS(Calculations!$Y:$Y, Calculations!$B:$B, A44, Calculations!$E:$E, ">=65"), "")

Sheet Checks and Equations
A1: Check Name | B1: Value | C1: Expected | D1: Status
A2: Equation of Value (Target = 0.8 * PV Net Contribs) | B2: =SUM(Calculations!$L:$L) * Parameters!$B$8 | C2: =SUM(Calculations!$X:$X) | D2: =IF(ABS(B2-C2)<0.01, "OK", "FAIL")
