Workbook
Name CarData: Parameters!$A$13:$I$20
Name Header: Parameters!$A$13:$I$13
Name HeaderCol: Parameters!$A$13:$A$20
Name TaxCO2: Parameters!$A$3:$D$8
Name TaxWeight: Parameters!$F$3:$H$8

Sheet Parameters
A1: Parameters
F2: Alternative
A3: Tax - CO2 (g/km) | C3: Year of purchase ($) | D3: Year 2-5 ($) | F3: Tax - Weight (kg) | H3: Amount ($)
A4: from | B4: to | F4: from | G4: to
A5: 0 | B5: 50 | C5: 0 | D5: 0 | F5: 0 | G5: 1500 | H5: 150
A6: 50 | B6: 150 | C6: =2*D6 | D6: 150 | F6: 1500 | G6: 2500 | H6: =H5*2
A7: 150 | B7: 200 | C7: =2*D7 | D7: 200 | F7: 2500 | G7: 3500 | H7: =H6*2
A8: 200 | C8: =2*D8 | D8: 300 | F8: 3500 | H8: =H7*2
A10: Kilometers per year | B10: 15000
A12: Car Specifications
B13: CO2 | C13: Fuel | D13: Battery capacity | E13: Range | F13: Weight | G13: Price | H13: Profit margin | I13: Annual service cost
B14: emitted per km (g) | C14: Consumption (litres per 100km) | D14: (kWh) | E14: * (km) | F14: (kg) | G14: ($) | I14: ($)
A15: Small Petrol | B15: 125 | C15: 6.4 | F15: 1900 | G15: 28450 | H15: 0.05 | I15: 250
A16: Medium Petrol | B16: 186 | C16: 7.7 | F16: 2070 | G16: 36866 | H16: 0.07 | I16: 300
A17: Large Petrol | B17: 215 | C17: 8.2 | F17: 2850 | G17: 65585 | H17: 0.11 | I17: 350
A18: Small Electric | B18: 0 | D18: 62 | E18: 264 | F18: 2270 | G18: 39465 | H18: 0.11 | I18: 100
A19: Medium Electric | B19: 0 | D19: 82 | E19: 315 | F19: 2540 | G19: 47825 | H19: 0.14 | I19: 150
A20: Large Electric | B20: 0 | D20: 96 | E20: 309 | F20: 3730 | G20: 68834 | H20: 0.18 | I20: 180
E21: * Distance travelled on full battery
B22: Base | C22: Alt
A23: Electricity cost per kWh ($) | B23: 0.28 | C23: =B23-0.05
A24: Fuel cost per litre ($) | B24: 1.5
A26: Discount rate | B26: 0.04
A27: Service cost from year | B27: 4

Sheet Data
A1: Vehicle Sales for the last year - number of cars sold each month
A3: Model | B3: Jan | C3: Feb | D3: Mar | E3: Apr | F3: May | G3: Jun | H3: Jul | I3: Aug | J3: Sep | K3: Oct | L3: Nov | M3: Dec | N3: Total
A4: Small Petrol | B4: 1296 | C4: 1111 | D4: 3190 | E4: 2198 | F4: 2335 | G4: 2804 | H4: 2076 | I4: 1947 | J4: 2423 | K4: 2228 | L4: 2380 | M4: 1579 | N4: =SUM(B4:M4)
A5: Medium Petrol | B5: 154 | C5: 63 | D5: 333 | E5: 163 | F5: 122 | G5: 204 | H5: 156 | I5: 46 | J5: 197 | K5: 102 | L5: 217 | M5: 136 | N5: =SUM(B5:M5)
A6: Large Petrol | B6: 163 | C6: 145 | D6: 621 | E6: 225 | F6: 177 | G6: 72 | H6: 53 | I6: 68 | J6: 162 | K6: 47 | L6: 31 | M6: 72 | N6: =SUM(B6:M6)
A7: Small Electric | B7: 719 | C7: 632 | D7: 1234 | E7: 890 | F7: 791 | G7: 733 | H7: 752 | I7: 636 | J7: 880 | K7: 1109 | L7: 1338 | M7: 1432 | N7: =SUM(B7:M7)
A8: Medium Electric | B8: 379 | C8: 252 | D8: 706 | E8: 618 | F8: 821 | G8: 261 | H8: 205 | I8: 254 | J8: 637 | K8: 749 | L8: 622 | M8: 787 | N8: =SUM(B8:M8)
A9: Large Electric | B9: 215 | C9: 82 | D9: 355 | E9: 178 | F9: 203 | G9: 149 | H9: 74 | I9: 139 | J9: 479 | K9: 510 | L9: 355 | M9: 1109 | N9: =SUM(B9:M9)
A10: Total | B10: =SUM(B4:B9) | C10: =SUM(C4:C9) | D10: =SUM(D4:D9) | E10: =SUM(E4:E9) | F10: =SUM(F4:F9) | G10: =SUM(G4:G9) | H10: =SUM(H4:H9) | I10: =SUM(I4:I9) | ... N10: =SUM(N4:N9)

Sheet Calculations-Base
A1: Base Scenario
A2: Calculates the total cost of ownership for all cars in the current range under the old tax regime.
B5: Small Petrol | H5: Medium Petrol | N5: Large Petrol
A6: Year | B6: Price | C6: Tax | D6: Annual service cost | E6: Fuel | F6: PV start | G6: PV mid | H6: Price | I6: Tax | J6: Annual service cost | K6: Fuel | L6: PV start | M6: PV mid | N6: Price | O6: Tax | P6: Annual service cost | Q6: Fuel | R6: PV start | S6: PV mid
A7: 1 | B7: =INDEX(CarData,MATCH($B$5,HeaderCol,0),MATCH(B$6,Header,0)) | C7: =VLOOKUP(INDEX(CarData,MATCH($B$5,HeaderCol,0),MATCH("CO2",Header,0)),TaxCO2,MIN($A7,2)+2,TRUE) | D7: =IF($A7>=Parameters!$B$27,INDEX(CarData,MATCH($B$5,HeaderCol,0),MATCH(D$6,Header,0)),0) | E7: =Parameters!$B$10*INDEX(CarData,MATCH($B$5,HeaderCol,0),MATCH("Fuel",Header,0))/100*Parameters!$B$24 | F7: =(B7+C7)*(1+Parameters!$B$26)^-($A7-1) | G7: =(D7+E7)*(1+Parameters!$B$26)^-($A7-0.5) | H7: =INDEX(CarData,MATCH($H$5,HeaderCol,0),MATCH(H$6,Header,0)) | I7: =VLOOKUP(INDEX(CarData,MATCH($H$5,HeaderCol,0),MATCH("CO2",Header,0)),TaxCO2,MIN($A7,2)+2,TRUE) | J7: =IF($A7>=Parameters!$B$27,INDEX(CarData,MATCH($H$5,HeaderCol,0),MATCH(J$6,Header,0)),0) | K7: =Parameters!$B$10*INDEX(CarData,MATCH($H$5,HeaderCol,0),MATCH("Fuel",Header,0))/100*Parameters!$B$24 | L7: =(H7+I7)*(1+Parameters!$B$26)^-($A7-1) | M7: =(J7+K7)*(1+Parameters!$B$26)^-($A7-0.5) | N7: =INDEX(CarData,MATCH($N$5,HeaderCol,0),MATCH(N$6,Header,0)) | O7: =VLOOKUP(INDEX(CarData,MATCH($N$5,HeaderCol,0),MATCH("CO2",Header,0)),TaxCO2,MIN($A7,2)+2,TRUE) | P7: =IF($A7>=Parameters!$B$27,INDEX(CarData,MATCH($N$5,HeaderCol,0),MATCH(P$6,Header,0)),0) | Q7: =Parameters!$B$10*INDEX(CarData,MATCH($N$5,HeaderCol,0),MATCH("Fuel",Header,0))/100*Parameters!$B$24 | R7: =(N7+O7)*(1+Parameters!$B$26)^-($A7-1) | S7: =(P7+Q7)*(1+Parameters!$B$26)^-($A7-0.5)
A8: 2 | C8: =VLOOKUP(INDEX(CarData,MATCH($B$5,HeaderCol,0),MATCH("CO2",Header,0)),TaxCO2,MIN($A8,2)+2,TRUE) | D8: =IF($A8>=Parameters!$B$27,INDEX(CarData,MATCH($B$5,HeaderCol,0),MATCH(D$6,Header,0)),0) | E8: =Parameters!$B$10*INDEX(CarData,MATCH($B$5,HeaderCol,0),MATCH("Fuel",Header,0))/100*Parameters!$B$24 | F8: =(B8+C8)*(1+Parameters!$B$26)^-($A8-1) | G8: =(D8+E8)*(1+Parameters!$B$26)^-($A8-0.5) | I8: =VLOOKUP(INDEX(CarData,MATCH($H$5,HeaderCol,0),MATCH("CO2",Header,0)),TaxCO2,MIN($A8,2)+2,TRUE) | J8: =IF($A8>=Parameters!$B$27,INDEX(CarData,MATCH($H$5,HeaderCol,0),MATCH(J$6,Header,0)),0) | K8: =Parameters!$B$10*INDEX(CarData,MATCH($H$5,HeaderCol,0),MATCH("Fuel",Header,0))/100*Parameters!$B$24 | L8: =(H8+I8)*(1+Parameters!$B$26)^-($A8-1) | M8: =(J8+K8)*(1+Parameters!$B$26)^-($A8-0.5) | O8: =VLOOKUP(INDEX(CarData,MATCH($N$5,HeaderCol,0),MATCH("CO2",Header,0)),TaxCO2,MIN($A8,2)+2,TRUE) | P8: =IF($A8>=Parameters!$B$27,INDEX(CarData,MATCH($N$5,HeaderCol,0),MATCH(P$6,Header,0)),0) | Q8: =Parameters!$B$10*INDEX(CarData,MATCH($N$5,HeaderCol,0),MATCH("Fuel",Header,0))/100*Parameters!$B$24 | R8: =(N8+O8)*(1+Parameters!$B$26)^-($A8-1) | S8: =(P8+Q8)*(1+Parameters!$B$26)^-($A8-0.5)
A9: 3 | C9: =VLOOKUP(INDEX(CarData,MATCH($B$5,HeaderCol,0),MATCH("CO2",Header,0)),TaxCO2,MIN($A9,2)+2,TRUE) | D9: =IF($A9>=Parameters!$B$27,INDEX(CarData,MATCH($B$5,HeaderCol,0),MATCH(D$6,Header,0)),0) | E9: =Parameters!$B$10*INDEX(CarData,MATCH($B$5,HeaderCol,0),MATCH("Fuel",Header,0))/100*Parameters!$B$24 | F9: =(B9+C9)*(1+Parameters!$B$26)^-($A9-1) | G9: =(D9+E9)*(1+Parameters!$B$26)^-($A9-0.5) | I9: =VLOOKUP(INDEX(CarData,MATCH($H$5,HeaderCol,0),MATCH("CO2",Header,0)),TaxCO2,MIN($A9,2)+2,TRUE) | J9: =IF($A9>=Parameters!$B$27,INDEX(CarData,MATCH($H$5,HeaderCol,0),MATCH(J$6,Header,0)),0) | K9: =Parameters!$B$10*INDEX(CarData,MATCH($H$5,HeaderCol,0),MATCH("Fuel",Header,0))/100*Parameters!$B$24 | L9: =(H9+I9)*(1+Parameters!$B$26)^-($A9-1) | M9: =(J9+K9)*(1+Parameters!$B$26)^-($A9-0.5) | O9: =VLOOKUP(INDEX(CarData,MATCH($N$5,HeaderCol,0),MATCH("CO2",Header,0)),TaxCO2,MIN($A9,2)+2,TRUE) | P9: =IF($A9>=Parameters!$B$27,INDEX(CarData,MATCH($N$5,HeaderCol,0),MATCH(P$6,Header,0)),0) | Q9: =Parameters!$B$10*INDEX(CarData,MATCH($N$5,HeaderCol,0),MATCH("Fuel",Header,0))/100*Parameters!$B$24 | R9: =(N9+O9)*(1+Parameters!$B$26)^-($A9-1) | S9: =(P9+Q9)*(1+Parameters!$B$26)^-($A9-0.5)
A10: 4 | C10: =VLOOKUP(INDEX(CarData,MATCH($B$5,HeaderCol,0),MATCH("CO2",Header,0)),TaxCO2,MIN($A10,2)+2,TRUE) | D10: =IF($A10>=Parameters!$B$27,INDEX(CarData,MATCH($B$5,HeaderCol,0),MATCH(D$6,Header,0)),0) | E10: =Parameters!$B$10*INDEX(CarData,MATCH($B$5,HeaderCol,0),MATCH("Fuel",Header,0))/100*Parameters!$B$24 | F10: =(B10+C10)*(1+Parameters!$B$26)^-($A10-1) | G10: =(D10+E10)*(1+Parameters!$B$26)^-($A10-0.5) | I10: =VLOOKUP(INDEX(CarData,MATCH($H$5,HeaderCol,0),MATCH("CO2",Header,0)),TaxCO2,MIN($A10,2)+2,TRUE) | J10: =IF($A10>=Parameters!$B$27,INDEX(CarData,MATCH($H$5,HeaderCol,0),MATCH(J$6,Header,0)),0) | K10: =Parameters!$B$10*INDEX(CarData,MATCH($H$5,HeaderCol,0),MATCH("Fuel",Header,0))/100*Parameters!$B$24 | L10: =(H10+I10)*(1+Parameters!$B$26)^-($A10-1) | M10: =(J10+K10)*(1+Parameters!$B$26)^-($A10-0.5) | O10: =VLOOKUP(INDEX(CarData,MATCH($N$5,HeaderCol,0),MATCH("CO2",Header,0)),TaxCO2,MIN($A10,2)+2,TRUE) | P10: =IF($A10>=Parameters!$B$27,INDEX(CarData,MATCH($N$5,HeaderCol,0),MATCH(P$6,Header,0)),0) | Q10: =Parameters!$B$10*INDEX(CarData,MATCH($N$5,HeaderCol,0),MATCH("Fuel",Header,0))/100*Parameters!$B$24 | R10: =(N10+O10)*(1+Parameters!$B$26)^-($A10-1) | S10: =(P10+Q10)*(1+Parameters!$B$26)^-($A10-0.5)
A11: 5 | C11: =VLOOKUP(INDEX(CarData,MATCH($B$5,HeaderCol,0),MATCH("CO2",Header,0)),TaxCO2,MIN($A11,2)+2,TRUE) | D11: =IF($A11>=Parameters!$B$27,INDEX(CarData,MATCH($B$5,HeaderCol,0),MATCH(D$6,Header,0)),0) | E11: =Parameters!$B$10*INDEX(CarData,MATCH($B$5,HeaderCol,0),MATCH("Fuel",Header,0))/100*Parameters!$B$24 | F11: =(B11+C11)*(1+Parameters!$B$26)^-($A11-1) | G11: =(D11+E11)*(1+Parameters!$B$26)^-($A11-0.5) | I11: =VLOOKUP(INDEX(CarData,MATCH($H$5,HeaderCol,0),MATCH("CO2",Header,0)),TaxCO2,MIN($A11,2)+2,TRUE) | J11: =IF($A11>=Parameters!$B$27,INDEX(CarData,MATCH($H$5,HeaderCol,0),MATCH(J$6,Header,0)),0) | K11: =Parameters!$B$10*INDEX(CarData,MATCH($H$5,HeaderCol,0),MATCH("Fuel",Header,0))/100*Parameters!$B$24 | L11: =(H11+I11)*(1+Parameters!$B$26)^-($A11-1) | M11: =(J11+K11)*(1+Parameters!$B$26)^-($A11-0.5) | O11: =VLOOKUP(INDEX(CarData,MATCH($N$5,HeaderCol,0),MATCH("CO2",Header,0)),TaxCO2,MIN($A11,2)+2,TRUE) | P11: =IF($A11>=Parameters!$B$27,INDEX(CarData,MATCH($N$5,HeaderCol,0),MATCH(P$6,Header,0)),0) | Q11: =Parameters!$B$10*INDEX(CarData,MATCH($N$5,HeaderCol,0),MATCH("Fuel",Header,0))/100*Parameters!$B$24 | R11: =(N11+O11)*(1+Parameters!$B$26)^-($A11-1) | S11: =(P11+Q11)*(1+Parameters!$B$26)^-($A11-0.5)
A13: Price of Car | G13: =B7 | M13: =H7 | S13: =N7
A14: PV Total cost of ownership | G14: =SUM(F7:G11) | M14: =SUM(L7:M11) | S14: =SUM(R7:S11)
A15: Profit | G15: =INDEX(CarData,MATCH($B$5,HeaderCol,0),MATCH("Profit Margin",Header,0))*G13 | M15: =INDEX(CarData,MATCH($H$5,HeaderCol,0),MATCH("Profit Margin",Header,0))*M13 | S15: =INDEX(CarData,MATCH($N$5,HeaderCol,0),MATCH("Profit Margin",Header,0))*S13
A16: Manufacturing costs | G16: =G13-G15 | M16: =M13-M15 | S16: =S13-S15
B19: Small Electric | H19: Medium Electric | N19: Large Electric
A20: Year | B20: Price | C20: Tax | D20: Annual service cost | E20: Electricity | F20: PV start | G20: PV mid | H20: Price | I20: Tax | J20: Annual service cost | K20: Electricity | L20: PV start | M20: PV mid | N20: Price | O20: Tax | P20: Annual service cost | Q20: Electricity | R20: PV start | S20: PV mid
A21: 1 | B21: =INDEX(CarData,MATCH($B$19,HeaderCol,0),MATCH(B$20,Header,0)) | C21: =VLOOKUP(INDEX(CarData,MATCH($B$19,HeaderCol,0),MATCH("CO2",Header,0)),TaxCO2,MIN($A21,2)+2,TRUE) | D21: =IF($A21>=Parameters!$B$27,INDEX(CarData,MATCH($B$19,HeaderCol,0),MATCH(D$6,Header,0)),0) | E21: =Parameters!$B$10/INDEX(CarData,MATCH($B$19,HeaderCol,0),MATCH("Range",Header,0))*INDEX(CarData,MATCH($B$19,HeaderCol,0),MATCH("Battery capacity",Header,0))*Parameters!$B$23 | F21: =(B21+C21)*(1+Parameters!$B$26)^-($A21-1) | G21: =(D21+E21)*(1+Parameters!$B$26)^-($A21-0.5) | H21: =INDEX(CarData,MATCH($H$19,HeaderCol,0),MATCH(H$6,Header,0)) | I21: =VLOOKUP(INDEX(CarData,MATCH($H$19,HeaderCol,0),MATCH("CO2",Header,0)),TaxCO2,MIN($A21,2)+2,TRUE) | J21: =IF($A21>=Parameters!$B$27,INDEX(CarData,MATCH($H$19,HeaderCol,0),MATCH(J$6,Header,0)),0) | K21: =Parameters!$B$10/INDEX(CarData,MATCH($H$19,HeaderCol,0),MATCH("Range",Header,0))*INDEX(CarData,MATCH($H$19,HeaderCol,0),MATCH("Battery capacity",Header,0))*Parameters!$B$23 | L21: =(H21+I21)*(1+Parameters!$B$26)^-($A21-1) | M21: =(J21+K21)*(1+Parameters!$B$26)^-($A21-0.5) | N21: =INDEX(CarData,MATCH($N$19,HeaderCol,0),MATCH(N$6,Header,0)) | O21: =VLOOKUP(INDEX(CarData,MATCH($N$19,HeaderCol,0),MATCH("CO2",Header,0)),TaxCO2,MIN($A21,2)+2,TRUE) | P21: =IF($A21>=Parameters!$B$27,INDEX(CarData,MATCH($N$19,HeaderCol,0),MATCH(P$6,Header,0)),0) | Q21: =Parameters!$B$10/INDEX(CarData,MATCH($N$19,HeaderCol,0),MATCH("Range",Header,0))*INDEX(CarData,MATCH($N$19,HeaderCol,0),MATCH("Battery capacity",Header,0))*Parameters!$B$23 | R21: =(N21+O21)*(1+Parameters!$B$26)^-($A21-1) | S21: =(P21+Q21)*(1+Parameters!$B$26)^-($A21-0.5)
A22: 2 | C22: =VLOOKUP(INDEX(CarData,MATCH($B$19,HeaderCol,0),MATCH("CO2",Header,0)),TaxCO2,MIN($A22,2)+2,TRUE) | D22: =IF($A22>=Parameters!$B$27,INDEX(CarData,MATCH($B$19,HeaderCol,0),MATCH(D$6,Header,0)),0) | E22: =Parameters!$B$10/INDEX(CarData,MATCH($B$19,HeaderCol,0),MATCH("Range",Header,0))*INDEX(CarData,MATCH($B$19,HeaderCol,0),MATCH("Battery capacity",Header,0))*Parameters!$B$23 | F22: =(B22+C22)*(1+Parameters!$B$26)^-($A22-1) | G22: =(D22+E22)*(1+Parameters!$B$26)^-($A22-0.5) | I22: =VLOOKUP(INDEX(CarData,MATCH($H$19,HeaderCol,0),MATCH("CO2",Header,0)),TaxCO2,MIN($A22,2)+2,TRUE) | J22: =IF($A22>=Parameters!$B$27,INDEX(CarData,MATCH($H$19,HeaderCol,0),MATCH(J$6,Header,0)),0) | K22: =Parameters!$B$10/INDEX(CarData,MATCH($H$19,HeaderCol,0),MATCH("Range",Header,0))*INDEX(CarData,MATCH($H$19,HeaderCol,0),MATCH("Battery capacity",Header,0))*Parameters!$B$23 | L22: =(H22+I22)*(1+Parameters!$B$26)^-($A22-1) | M22: =(J22+K22)*(1+Parameters!$B$26)^-($A22-0.5) | O22: =VLOOKUP(INDEX(CarData,MATCH($N$19,HeaderCol,0),MATCH("CO2",Header,0)),TaxCO2,MIN($A22,2)+2,TRUE) | P22: =IF($A22>=Parameters!$B$27,INDEX(CarData,MATCH($N$19,HeaderCol,0),MATCH(P$6,Header,0)),0) | Q22: =Parameters!$B$10/INDEX(CarData,MATCH($N$19,HeaderCol,0),MATCH("Range",Header,0))*INDEX(CarData,MATCH($N$19,HeaderCol,0),MATCH("Battery capacity",Header,0))*Parameters!$B$23 | R22: =(N22+O22)*(1+Parameters!$B$26)^-($A22-1) | S22: =(P22+Q22)*(1+Parameters!$B$26)^-($A22-0.5)
A23: 3 | C23: =VLOOKUP(INDEX(CarData,MATCH($B$19,HeaderCol,0),MATCH("CO2",Header,0)),TaxCO2,MIN($A23,2)+2,TRUE) | D23: =IF($A23>=Parameters!$B$27,INDEX(CarData,MATCH($B$19,HeaderCol,0),MATCH(D$6,Header,0)),0) | E23: =Parameters!$B$10/INDEX(CarData,MATCH($B$19,HeaderCol,0),MATCH("Range",Header,0))*INDEX(CarData,MATCH($B$19,HeaderCol,0),MATCH("Battery capacity",Header,0))*Parameters!$B$23 | F23: =(B23+C23)*(1+Parameters!$B$26)^-($A23-1) | G23: =(D23+E23)*(1+Parameters!$B$26)^-($A23-0.5) | I23: =VLOOKUP(INDEX(CarData,MATCH($H$19,HeaderCol,0),MATCH("CO2",Header,0)),TaxCO2,MIN($A23,2)+2,TRUE) | J23: =IF($A23>=Parameters!$B$27,INDEX(CarData,MATCH($H$19,HeaderCol,0),MATCH(J$6,Header,0)),0) | K23: =Parameters!$B$10/INDEX(CarData,MATCH($H$19,HeaderCol,0),MATCH("Range",Header,0))*INDEX(CarData,MATCH($H$19,HeaderCol,0),MATCH("Battery capacity",Header,0))*Parameters!$B$23 | L23: =(H23+I23)*(1+Parameters!$B$26)^-($A23-1) | M23: =(J23+K23)*(1+Parameters!$B$26)^-($A23-0.5) | O23: =VLOOKUP(INDEX(CarData,MATCH($N$19,HeaderCol,0),MATCH("CO2",Header,0)),TaxCO2,MIN($A23,2)+2,TRUE) | P23: =IF($A23>=Parameters!$B$27,INDEX(CarData,MATCH($N$19,HeaderCol,0),MATCH(P$6,Header,0)),0) | Q23: =Parameters!$B$10/INDEX(CarData,MATCH($N$19,HeaderCol,0),MATCH("Range",Header,0))*INDEX(CarData,MATCH($N$19,HeaderCol,0),MATCH("Battery capacity",Header,0))*Parameters!$B$23 | R23: =(N23+O23)*(1+Parameters!$B$26)^-($A23-1) | S23: =(P23+Q23)*(1+Parameters!$B$26)^-($A23-0.5)
A24: 4 | C24: =VLOOKUP(INDEX(CarData,MATCH($B$19,HeaderCol,0),MATCH("CO2",Header,0)),TaxCO2,MIN($A24,2)+2,TRUE) | D24: =IF($A24>=Parameters!$B$27,INDEX(CarData,MATCH($B$19,HeaderCol,0),MATCH(D$6,Header,0)),0) | E24: =Parameters!$B$10/INDEX(CarData,MATCH($B$19,HeaderCol,0),MATCH("Range",Header,0))*INDEX(CarData,MATCH($B$19,HeaderCol,0),MATCH("Battery capacity",Header,0))*Parameters!$B$23 | F24: =(B24+C24)*(1+Parameters!$B$26)^-($A24-1) | G24: =(D24+E24)*(1+Parameters!$B$26)^-($A24-0.5) | I24: =VLOOKUP(INDEX(CarData,MATCH($H$19,HeaderCol,0),MATCH("CO2",Header,0)),TaxCO2,MIN($A24,2)+2,TRUE) | J24: =IF($A24>=Parameters!$B$27,INDEX(CarData,MATCH($H$19,HeaderCol,0),MATCH(J$6,Header,0)),0) | K24: =Parameters!$B$10/INDEX(CarData,MATCH($H$19,HeaderCol,0),MATCH("Range",Header,0))*INDEX(CarData,MATCH($H$19,HeaderCol,0),MATCH("Battery capacity",Header,0))*Parameters!$B$23 | L24: =(H24+I24)*(1+Parameters!$B$26)^-($A24-1) | M24: =(J24+K24)*(1+Parameters!$B$26)^-($A24-0.5) | O24: =VLOOKUP(INDEX(CarData,MATCH($N$19,HeaderCol,0),MATCH("CO2",Header,0)),TaxCO2,MIN($A24,2)+2,TRUE) | P24: =IF($A24>=Parameters!$B$27,INDEX(CarData,MATCH($N$19,HeaderCol,0),MATCH(P$6,Header,0)),0) | Q24: =Parameters!$B$10/INDEX(CarData,MATCH($N$19,HeaderCol,0),MATCH("Range",Header,0))*INDEX(CarData,MATCH($N$19,HeaderCol,0),MATCH("Battery capacity",Header,0))*Parameters!$B$23 | R24: =(N24+O24)*(1+Parameters!$B$26)^-($A24-1) | S24: =(P24+Q24)*(1+Parameters!$B$26)^-($A24-0.5)
A25: 5 | C25: =VLOOKUP(INDEX(CarData,MATCH($B$19,HeaderCol,0),MATCH("CO2",Header,0)),TaxCO2,MIN($A25,2)+2,TRUE) | D25: =IF($A25>=Parameters!$B$27,INDEX(CarData,MATCH($B$19,HeaderCol,0),MATCH(D$6,Header,0)),0) | E25: =Parameters!$B$10/INDEX(CarData,MATCH($B$19,HeaderCol,0),MATCH("Range",Header,0))*INDEX(CarData,MATCH($B$19,HeaderCol,0),MATCH("Battery capacity",Header,0))*Parameters!$B$23 | F25: =(B25+C25)*(1+Parameters!$B$26)^-($A25-1) | G25: =(D25+E25)*(1+Parameters!$B$26)^-($A25-0.5) | I25: =VLOOKUP(INDEX(CarData,MATCH($H$19,HeaderCol,0),MATCH("CO2",Header,0)),TaxCO2,MIN($A25,2)+2,TRUE) | J25: =IF($A25>=Parameters!$B$27,INDEX(CarData,MATCH($H$19,HeaderCol,0),MATCH(J$6,Header,0)),0) | K25: =Parameters!$B$10/INDEX(CarData,MATCH($H$19,HeaderCol,0),MATCH("Range",Header,0))*INDEX(CarData,MATCH($H$19,HeaderCol,0),MATCH("Battery capacity",Header,0))*Parameters!$B$23 | L25: =(H25+I25)*(1+Parameters!$B$26)^-($A25-1) | M25: =(J25+K25)*(1+Parameters!$B$26)^-($A25-0.5) | O25: =VLOOKUP(INDEX(CarData,MATCH($N$19,HeaderCol,0),MATCH("CO2",Header,0)),TaxCO2,MIN($A25,2)+2,TRUE) | P25: =IF($A25>=Parameters!$B$27,INDEX(CarData,MATCH($N$19,HeaderCol,0),MATCH(P$6,Header,0)),0) | Q25: =Parameters!$B$10/INDEX(CarData,MATCH($N$19,HeaderCol,0),MATCH("Range",Header,0))*INDEX(CarData,MATCH($N$19,HeaderCol,0),MATCH("Battery capacity",Header,0))*Parameters!$B$23 | R25: =(N25+O25)*(1+Parameters!$B$26)^-($A25-1) | S25: =(P25+Q25)*(1+Parameters!$B$26)^-($A25-0.5)
A27: Price of Car | G27: =B21 | M27: =H21 | S27: =N21
A28: PV Total cost of ownership | G28: =SUM(F21:G25) | M28: =SUM(L21:M25) | S28: =SUM(R21:S25)
A29: Profit | G29: =INDEX(CarData,MATCH($B$19,HeaderCol,0),MATCH("Profit Margin",Header,0))*G27 | M29: =INDEX(CarData,MATCH($H$19,HeaderCol,0),MATCH("Profit Margin",Header,0))*M27 | S29: =INDEX(CarData,MATCH($N$19,HeaderCol,0),MATCH("Profit Margin",Header,0))*S27
A30: Manufacturing costs | G30: =G27-G29 | M30: =M27-M29 | S30: =S27-S29

Sheet Total profit-Base
A1: Profit calculations
B3: Sales | C3: Profit | D3: Revenue | E3: Cost of Ownership | F3: Manufacturing costs
A4: Small Petrol | B4: =INDEX(Data!N:N,MATCH($A4,Data!A:A,0)) | C4: =$B4*'Calculations-Base'!G15 | D4: =$B4*'Calculations-Base'!$G13 | E4: =$B4*'Calculations-Base'!$G14 | F4: =$B4*'Calculations-Base'!$G16
A5: Medium Petrol | B5: =INDEX(Data!N:N,MATCH($A5,Data!A:A,0)) | C5: =$B5*'Calculations-Base'!M15 | D5: =$B5*'Calculations-Base'!$M13 | E5: =$B5*'Calculations-Base'!$M14 | F5: =$B5*'Calculations-Base'!$M16
A6: Large Petrol | B6: =INDEX(Data!N:N,MATCH($A6,Data!A:A,0)) | C6: =$B6*'Calculations-Base'!S15 | D6: =$B6*'Calculations-Base'!$S13 | E6: =$B6*'Calculations-Base'!$S14 | F6: =$B6*'Calculations-Base'!$S16
A7: Small Electric | B7: =INDEX(Data!N:N,MATCH($A7,Data!A:A,0)) | C7: =$B7*'Calculations-Base'!G29 | D7: =$B7*'Calculations-Base'!$G27 | E7: =$B7*'Calculations-Base'!$G28 | F7: =$B7*'Calculations-Base'!$G30
A8: Medium Electric | B8: =INDEX(Data!N:N,MATCH($A8,Data!A:A,0)) | C8: =$B8*'Calculations-Base'!M29 | D8: =$B8*'Calculations-Base'!$M27 | E8: =$B8*'Calculations-Base'!$M28 | F8: =$B8*'Calculations-Base'!$M30
A9: Large Electric | B9: =INDEX(Data!N:N,MATCH($A9,Data!A:A,0)) | C9: =$B9*'Calculations-Base'!S29 | D9: =$B9*'Calculations-Base'!$S27 | E9: =$B9*'Calculations-Base'!$S28 | F9: =$B9*'Calculations-Base'!$S30
A11: Total | B11: =SUM(B4:B10) | C11: =SUM(C4:C10) | D11: =SUM(D4:D10) | E11: =SUM(E4:E10) | F11: =SUM(F4:F10)
A13: Check total sales: | B13: =IF(B11=Data!$N$10,"OK","Check")

Sheet Calculations-Weight
A1: Tax based on Weight
A2: Calculates the total cost of ownership for all cars in the current range under the new tax regime.
B5: Small Petrol | H5: Medium Petrol | N5: Large Petrol
A6: Year | B6: Price | C6: Tax | D6: Annual service cost | E6: Fuel | F6: PV start | G6: PV mid | H6: Price | I6: Tax | J6: Annual service cost | K6: Fuel | L6: PV start | M6: PV mid | N6: Price | O6: Tax | P6: Annual service cost | Q6: Fuel | R6: PV start | S6: PV mid
A7: 1 | B7: =INDEX(CarData,MATCH($B$5,HeaderCol,0),MATCH(B$6,Header,0)) | C7: =VLOOKUP(INDEX(CarData,MATCH($B$5,HeaderCol,0),MATCH("Weight",Header,0)),TaxWeight,3,TRUE) | D7: =IF($A7>=Parameters!$B$27,INDEX(CarData,MATCH($B$5,HeaderCol,0),MATCH(D$6,Header,0)),0) | E7: =Parameters!$B$10*INDEX(CarData,MATCH($B$5,HeaderCol,0),MATCH("Fuel",Header,0))/100*Parameters!$B$24 | F7: =(B7+C7)*(1+Parameters!$B$26)^-($A7-1) | G7: =(D7+E7)*(1+Parameters!$B$26)^-($A7-0.5) | H7: =INDEX(CarData,MATCH($H$5,HeaderCol,0),MATCH(H$6,Header,0)) | I7: =VLOOKUP(INDEX(CarData,MATCH($H$5,HeaderCol,0),MATCH("Weight",Header,0)),TaxWeight,3,TRUE) | J7: =IF($A7>=Parameters!$B$27,INDEX(CarData,MATCH($H$5,HeaderCol,0),MATCH(J$6,Header,0)),0) | K7: =Parameters!$B$10*INDEX(CarData,MATCH($H$5,HeaderCol,0),MATCH("Fuel",Header,0))/100*Parameters!$B$24 | L7: =(H7+I7)*(1+Parameters!$B$26)^-($A7-1) | M7: =(J7+K7)*(1+Parameters!$B$26)^-($A7-0.5) | N7: =INDEX(CarData,MATCH($N$5,HeaderCol,0),MATCH(N$6,Header,0)) | O7: =VLOOKUP(INDEX(CarData,MATCH($N$5,HeaderCol,0),MATCH("Weight",Header,0)),TaxWeight,3,TRUE) | P7: =IF($A7>=Parameters!$B$27,INDEX(CarData,MATCH($N$5,HeaderCol,0),MATCH(P$6,Header,0)),0) | Q7: =Parameters!$B$10*INDEX(CarData,MATCH($N$5,HeaderCol,0),MATCH("Fuel",Header,0))/100*Parameters!$B$24 | R7: =(N7+O7)*(1+Parameters!$B$26)^-($A7-1) | S7: =(P7+Q7)*(1+Parameters!$B$26)^-($A7-0.5)
A8: 2 | C8: =VLOOKUP(INDEX(CarData,MATCH($B$5,HeaderCol,0),MATCH("Weight",Header,0)),TaxWeight,3,TRUE) | D8: =IF($A8>=Parameters!$B$27,INDEX(CarData,MATCH($B$5,HeaderCol,0),MATCH(D$6,Header,0)),0) | E8: =Parameters!$B$10*INDEX(CarData,MATCH($B$5,HeaderCol,0),MATCH("Fuel",Header,0))/100*Parameters!$B$24 | F8: =(B8+C8)*(1+Parameters!$B$26)^-($A8-1) | G8: =(D8+E8)*(1+Parameters!$B$26)^-($A8-0.5) | I8: =VLOOKUP(INDEX(CarData,MATCH($H$5,HeaderCol,0),MATCH("Weight",Header,0)),TaxWeight,3,TRUE) | J8: =IF($A8>=Parameters!$B$27,INDEX(CarData,MATCH($H$5,HeaderCol,0),MATCH(J$6,Header,0)),0) | K8: =Parameters!$B$10*INDEX(CarData,MATCH($H$5,HeaderCol,0),MATCH("Fuel",Header,0))/100*Parameters!$B$24 | L8: =(H8+I8)*(1+Parameters!$B$26)^-($A8-1) | M8: =(J8+K8)*(1+Parameters!$B$26)^-($A8-0.5) | O8: =VLOOKUP(INDEX(CarData,MATCH($N$5,HeaderCol,0),MATCH("Weight",Header,0)),TaxWeight,3,TRUE) | P8: =IF($A8>=Parameters!$B$27,INDEX(CarData,MATCH($N$5,HeaderCol,0),MATCH(P$6,Header,0)),0) | Q8: =Parameters!$B$10*INDEX(CarData,MATCH($N$5,HeaderCol,0),MATCH("Fuel",Header,0))/100*Parameters!$B$24 | R8: =(N8+O8)*(1+Parameters!$B$26)^-($A8-1) | S8: =(P8+Q8)*(1+Parameters!$B$26)^-($A8-0.5)
A9: 3 | C9: =VLOOKUP(INDEX(CarData,MATCH($B$5,HeaderCol,0),MATCH("Weight",Header,0)),TaxWeight,3,TRUE) | D9: =IF($A9>=Parameters!$B$27,INDEX(CarData,MATCH($B$5,HeaderCol,0),MATCH(D$6,Header,0)),0) | E9: =Parameters!$B$10*INDEX(CarData,MATCH($B$5,HeaderCol,0),MATCH("Fuel",Header,0))/100*Parameters!$B$24 | F9: =(B9+C9)*(1+Parameters!$B$26)^-($A9-1) | G9: =(D9+E9)*(1+Parameters!$B$26)^-($A9-0.5) | I9: =VLOOKUP(INDEX(CarData,MATCH($H$5,HeaderCol,0),MATCH("Weight",Header,0)),TaxWeight,3,TRUE) | J9: =IF($A9>=Parameters!$B$27,INDEX(CarData,MATCH($H$5,HeaderCol,0),MATCH(J$6,Header,0)),0) | K9: =Parameters!$B$10*INDEX(CarData,MATCH($H$5,HeaderCol,0),MATCH("Fuel",Header,0))/100*Parameters!$B$24 | L9: =(H9+I9)*(1+Parameters!$B$26)^-($A9-1) | M9: =(J9+K9)*(1+Parameters!$B$26)^-($A9-0.5) | O9: =VLOOKUP(INDEX(CarData,MATCH($N$5,HeaderCol,0),MATCH("Weight",Header,0)),TaxWeight,3,TRUE) | P9: =IF($A9>=Parameters!$B$27,INDEX(CarData,MATCH($N$5,HeaderCol,0),MATCH(P$6,Header,0)),0) | Q9: =Parameters!$B$10*INDEX(CarData,MATCH($N$5,HeaderCol,0),MATCH("Fuel",Header,0))/100*Parameters!$B$24 | R9: =(N9+O9)*(1+Parameters!$B$26)^-($A9-1) | S9: =(P9+Q9)*(1+Parameters!$B$26)^-($A9-0.5)
A10: 4 | C10: =VLOOKUP(INDEX(CarData,MATCH($B$5,HeaderCol,0),MATCH("Weight",Header,0)),TaxWeight,3,TRUE) | D10: =IF($A10>=Parameters!$B$27,INDEX(CarData,MATCH($B$5,HeaderCol,0),MATCH(D$6,Header,0)),0) | E10: =Parameters!$B$10*INDEX(CarData,MATCH($B$5,HeaderCol,0),MATCH("Fuel",Header,0))/100*Parameters!$B$24 | F10: =(B10+C10)*(1+Parameters!$B$26)^-($A10-1) | G10: =(D10+E10)*(1+Parameters!$B$26)^-($A10-0.5) | I10: =VLOOKUP(INDEX(CarData,MATCH($H$5,HeaderCol,0),MATCH("Weight",Header,0)),TaxWeight,3,TRUE) | J10: =IF($A10>=Parameters!$B$27,INDEX(CarData,MATCH($H$5,HeaderCol,0),MATCH(J$6,Header,0)),0) | K10: =Parameters!$B$10*INDEX(CarData,MATCH($H$5,HeaderCol,0),MATCH("Fuel",Header,0))/100*Parameters!$B$24 | L10: =(H10+I10)*(1+Parameters!$B$26)^-($A10-1) | M10: =(J10+K10)*(1+Parameters!$B$26)^-($A10-0.5) | O10: =VLOOKUP(INDEX(CarData,MATCH($N$5,HeaderCol,0),MATCH("Weight",Header,0)),TaxWeight,3,TRUE) | P10: =IF($A10>=Parameters!$B$27,INDEX(CarData,MATCH($N$5,HeaderCol,0),MATCH(P$6,Header,0)),0) | Q10: =Parameters!$B$10*INDEX(CarData,MATCH($N$5,HeaderCol,0),MATCH("Fuel",Header,0))/100*Parameters!$B$24 | R10: =(N10+O10)*(1+Parameters!$B$26)^-($A10-1) | S10: =(P10+Q10)*(1+Parameters!$B$26)^-($A10-0.5)
A11: 5 | C11: =VLOOKUP(INDEX(CarData,MATCH($B$5,HeaderCol,0),MATCH("Weight",Header,0)),TaxWeight,3,TRUE) | D11: =IF($A11>=Parameters!$B$27,INDEX(CarData,MATCH($B$5,HeaderCol,0),MATCH(D$6,Header,0)),0) | E11: =Parameters!$B$10*INDEX(CarData,MATCH($B$5,HeaderCol,0),MATCH("Fuel",Header,0))/100*Parameters!$B$24 | F11: =(B11+C11)*(1+Parameters!$B$26)^-($A11-1) | G11: =(D11+E11)*(1+Parameters!$B$26)^-($A11-0.5) | I11: =VLOOKUP(INDEX(CarData,MATCH($H$5,HeaderCol,0),MATCH("Weight",Header,0)),TaxWeight,3,TRUE) | J11: =IF($A11>=Parameters!$B$27,INDEX(CarData,MATCH($H$5,HeaderCol,0),MATCH(J$6,Header,0)),0) | K11: =Parameters!$B$10*INDEX(CarData,MATCH($H$5,HeaderCol,0),MATCH("Fuel",Header,0))/100*Parameters!$B$24 | L11: =(H11+I11)*(1+Parameters!$B$26)^-($A11-1) | M11: =(J11+K11)*(1+Parameters!$B$26)^-($A11-0.5) | O11: =VLOOKUP(INDEX(CarData,MATCH($N$5,HeaderCol,0),MATCH("Weight",Header,0)),TaxWeight,3,TRUE) | P11: =IF($A11>=Parameters!$B$27,INDEX(CarData,MATCH($N$5,HeaderCol,0),MATCH(P$6,Header,0)),0) | Q11: =Parameters!$B$10*INDEX(CarData,MATCH($N$5,HeaderCol,0),MATCH("Fuel",Header,0))/100*Parameters!$B$24 | R11: =(N11+O11)*(1+Parameters!$B$26)^-($A11-1) | S11: =(P11+Q11)*(1+Parameters!$B$26)^-($A11-0.5)
A13: Price of Car | G13: =B7 | M13: =H7 | S13: =N7
A14: PV Total cost of ownership | G14: =SUM(F7:G11) | M14: =SUM(L7:M11) | S14: =SUM(R7:S11)
A15: Profit | G15: =INDEX(CarData,MATCH($B$5,HeaderCol,0),MATCH("Profit Margin",Header,0))*G13 | M15: =INDEX(CarData,MATCH($H$5,HeaderCol,0),MATCH("Profit Margin",Header,0))*M13 | S15: =INDEX(CarData,MATCH($N$5,HeaderCol,0),MATCH("Profit Margin",Header,0))*S13
A16: Manufacturing costs | G16: =G13-G15 | M16: =M13-M15 | S16: =S13-S15
B19: Small Electric | H19: Medium Electric | N19: Large Electric
A20: Year | B20: Price | C20: Tax | D20: Annual service cost | E20: Electricity | F20: PV start | G20: PV mid | H20: Price | I20: Tax | J20: Annual service cost | K20: Electricity | L20: PV start | M20: PV mid | N20: Price | O20: Tax | P20: Annual service cost | Q20: Electricity | R20: PV start | S20: PV mid
A21: 1 | B21: =INDEX(CarData,MATCH($B$19,HeaderCol,0),MATCH(B$20,Header,0)) | C21: =VLOOKUP(INDEX(CarData,MATCH($B$19,HeaderCol,0),MATCH("Weight",Header,0)),TaxWeight,3,TRUE) | D21: =IF($A21>=Parameters!$B$27,INDEX(CarData,MATCH($B$19,HeaderCol,0),MATCH(D$6,Header,0)),0) | E21: =Parameters!$B$10/INDEX(CarData,MATCH($B$19,HeaderCol,0),MATCH("Range",Header,0))*INDEX(CarData,MATCH($B$19,HeaderCol,0),MATCH("Battery capacity",Header,0))*(Parameters!$C$23) | F21: =(B21+C21)*(1+Parameters!$B$26)^-($A21-1) | G21: =(D21+E21)*(1+Parameters!$B$26)^-($A21-0.5) | H21: =INDEX(CarData,MATCH($H$19,HeaderCol,0),MATCH(H$6,Header,0)) | I21: =VLOOKUP(INDEX(CarData,MATCH($H$19,HeaderCol,0),MATCH("Weight",Header,0)),TaxWeight,3,TRUE) | J21: =IF($A21>=Parameters!$B$27,INDEX(CarData,MATCH($H$19,HeaderCol,0),MATCH(J$6,Header,0)),0) | K21: =Parameters!$B$10/INDEX(CarData,MATCH($H$19,HeaderCol,0),MATCH("Range",Header,0))*INDEX(CarData,MATCH($H$19,HeaderCol,0),MATCH("Battery capacity",Header,0))*Parameters!$C$23 | L21: =(H21+I21)*(1+Parameters!$B$26)^-($A21-1) | M21: =(J21+K21)*(1+Parameters!$B$26)^-($A21-0.5) | N21: =INDEX(CarData,MATCH($N$19,HeaderCol,0),MATCH(N$6,Header,0)) | O21: =VLOOKUP(INDEX(CarData,MATCH($N$19,HeaderCol,0),MATCH("Weight",Header,0)),TaxWeight,3,TRUE) | P21: =IF($A21>=Parameters!$B$27,INDEX(CarData,MATCH($N$19,HeaderCol,0),MATCH(P$6,Header,0)),0) | Q21: =Parameters!$B$10/INDEX(CarData,MATCH($N$19,HeaderCol,0),MATCH("Range",Header,0))*INDEX(CarData,MATCH($N$19,HeaderCol,0),MATCH("Battery capacity",Header,0))*Parameters!$C$23 | R21: =(N21+O21)*(1+Parameters!$B$26)^-($A21-1) | S21: =(P21+Q21)*(1+Parameters!$B$26)^-($A21-0.5)
A22: 2 | C22: =VLOOKUP(INDEX(CarData,MATCH($B$19,HeaderCol,0),MATCH("Weight",Header,0)),TaxWeight,3,TRUE) | D22: =IF($A22>=Parameters!$B$27,INDEX(CarData,MATCH($B$19,HeaderCol,0),MATCH(D$6,Header,0)),0) | E22: =Parameters!$B$10/INDEX(CarData,MATCH($B$19,HeaderCol,0),MATCH("Range",Header,0))*INDEX(CarData,MATCH($B$19,HeaderCol,0),MATCH("Battery capacity",Header,0))*(Parameters!$C$23) | F22: =(B22+C22)*(1+Parameters!$B$26)^-($A22-1) | G22: =(D22+E22)*(1+Parameters!$B$26)^-($A22-0.5) | I22: =VLOOKUP(INDEX(CarData,MATCH($H$19,HeaderCol,0),MATCH("Weight",Header,0)),TaxWeight,3,TRUE) | J22: =IF($A22>=Parameters!$B$27,INDEX(CarData,MATCH($H$19,HeaderCol,0),MATCH(J$6,Header,0)),0) | K22: =Parameters!$B$10/INDEX(CarData,MATCH($H$19,HeaderCol,0),MATCH("Range",Header,0))*INDEX(CarData,MATCH($H$19,HeaderCol,0),MATCH("Battery capacity",Header,0))*Parameters!$C$23 | L22: =(H22+I22)*(1+Parameters!$B$26)^-($A22-1) | M22: =(J22+K22)*(1+Parameters!$B$26)^-($A22-0.5) | O22: =VLOOKUP(INDEX(CarData,MATCH($N$19,HeaderCol,0),MATCH("Weight",Header,0)),TaxWeight,3,TRUE) | P22: =IF($A22>=Parameters!$B$27,INDEX(CarData,MATCH($N$19,HeaderCol,0),MATCH(P$6,Header,0)),0) | Q22: =Parameters!$B$10/INDEX(CarData,MATCH($N$19,HeaderCol,0),MATCH("Range",Header,0))*INDEX(CarData,MATCH($N$19,HeaderCol,0),MATCH("Battery capacity",Header,0))*Parameters!$C$23 | R22: =(N22+O22)*(1+Parameters!$B$26)^-($A22-1) | S22: =(P22+Q22)*(1+Parameters!$B$26)^-($A22-0.5)
A23: 3 | C23: =VLOOKUP(INDEX(CarData,MATCH($B$19,HeaderCol,0),MATCH("Weight",Header,0)),TaxWeight,3,TRUE) | D23: =IF($A23>=Parameters!$B$27,INDEX(CarData,MATCH($B$19,HeaderCol,0),MATCH(D$6,Header,0)),0) | E23: =Parameters!$B$10/INDEX(CarData,MATCH($B$19,HeaderCol,0),MATCH("Range",Header,0))*INDEX(CarData,MATCH($B$19,HeaderCol,0),MATCH("Battery capacity",Header,0))*(Parameters!$C$23) | F23: =(B23+C23)*(1+Parameters!$B$26)^-($A23-1) | G23: =(D23+E23)*(1+Parameters!$B$26)^-($A23-0.5) | I23: =VLOOKUP(INDEX(CarData,MATCH($H$19,HeaderCol,0),MATCH("Weight",Header,0)),TaxWeight,3,TRUE) | J23: =IF($A23>=Parameters!$B$27,INDEX(CarData,MATCH($H$19,HeaderCol,0),MATCH(J$6,Header,0)),0) | K23: =Parameters!$B$10/INDEX(CarData,MATCH($H$19,HeaderCol,0),MATCH("Range",Header,0))*INDEX(CarData,MATCH($H$19,HeaderCol,0),MATCH("Battery capacity",Header,0))*Parameters!$C$23 | L23: =(H23+I23)*(1+Parameters!$B$26)^-($A23-1) | M23: =(J23+K23)*(1+Parameters!$B$26)^-($A23-0.5) | O23: =VLOOKUP(INDEX(CarData,MATCH($N$19,HeaderCol,0),MATCH("Weight",Header,0)),TaxWeight,3,TRUE) | P23: =IF($A23>=Parameters!$B$27,INDEX(CarData,MATCH($N$19,HeaderCol,0),MATCH(P$6,Header,0)),0) | Q23: =Parameters!$B$10/INDEX(CarData,MATCH($N$19,HeaderCol,0),MATCH("Range",Header,0))*INDEX(CarData,MATCH($N$19,HeaderCol,0),MATCH("Battery capacity",Header,0))*Parameters!$C$23 | R23: =(N23+O23)*(1+Parameters!$B$26)^-($A23-1) | S23: =(P23+Q23)*(1+Parameters!$B$26)^-($A23-0.5)
A24: 4 | C24: =VLOOKUP(INDEX(CarData,MATCH($B$19,HeaderCol,0),MATCH("Weight",Header,0)),TaxWeight,3,TRUE) | D24: =IF($A24>=Parameters!$B$27,INDEX(CarData,MATCH($B$19,HeaderCol,0),MATCH(D$6,Header,0)),0) | E24: =Parameters!$B$10/INDEX(CarData,MATCH($B$19,HeaderCol,0),MATCH("Range",Header,0))*INDEX(CarData,MATCH($B$19,HeaderCol,0),MATCH("Battery capacity",Header,0))*(Parameters!$C$23) | F24: =(B24+C24)*(1+Parameters!$B$26)^-($A24-1) | G24: =(D24+E24)*(1+Parameters!$B$26)^-($A24-0.5) | I24: =VLOOKUP(INDEX(CarData,MATCH($H$19,HeaderCol,0),MATCH("Weight",Header,0)),TaxWeight,3,TRUE) | J24: =IF($A24>=Parameters!$B$27,INDEX(CarData,MATCH($H$19,HeaderCol,0),MATCH(J$6,Header,0)),0) | K24: =Parameters!$B$10/INDEX(CarData,MATCH($H$19,HeaderCol,0),MATCH("Range",Header,0))*INDEX(CarData,MATCH($H$19,HeaderCol,0),MATCH("Battery capacity",Header,0))*Parameters!$C$23 | L24: =(H24+I24)*(1+Parameters!$B$26)^-($A24-1) | M24: =(J24+K24)*(1+Parameters!$B$26)^-($A24-0.5) | O24: =VLOOKUP(INDEX(CarData,MATCH($N$19,HeaderCol,0),MATCH("Weight",Header,0)),TaxWeight,3,TRUE) | P24: =IF($A24>=Parameters!$B$27,INDEX(CarData,MATCH($N$19,HeaderCol,0),MATCH(P$6,Header,0)),0) | Q24: =Parameters!$B$10/INDEX(CarData,MATCH($N$19,HeaderCol,0),MATCH("Range",Header,0))*INDEX(CarData,MATCH($N$19,HeaderCol,0),MATCH("Battery capacity",Header,0))*Parameters!$C$23 | R24: =(N24+O24)*(1+Parameters!$B$26)^-($A24-1) | S24: =(P24+Q24)*(1+Parameters!$B$26)^-($A24-0.5)
A25: 5 | C25: =VLOOKUP(INDEX(CarData,MATCH($B$19,HeaderCol,0),MATCH("Weight",Header,0)),TaxWeight,3,TRUE) | D25: =IF($A25>=Parameters!$B$27,INDEX(CarData,MATCH($B$19,HeaderCol,0),MATCH(D$6,Header,0)),0) | E25: =Parameters!$B$10/INDEX(CarData,MATCH($B$19,HeaderCol,0),MATCH("Range",Header,0))*INDEX(CarData,MATCH($B$19,HeaderCol,0),MATCH("Battery capacity",Header,0))*(Parameters!$C$23) | F25: =(B25+C25)*(1+Parameters!$B$26)^-($A25-1) | G25: =(D25+E25)*(1+Parameters!$B$26)^-($A25-0.5) | I25: =VLOOKUP(INDEX(CarData,MATCH($H$19,HeaderCol,0),MATCH("Weight",Header,0)),TaxWeight,3,TRUE) | J25: =IF($A25>=Parameters!$B$27,INDEX(CarData,MATCH($H$19,HeaderCol,0),MATCH(J$6,Header,0)),0) | K25: =Parameters!$B$10/INDEX(CarData,MATCH($H$19,HeaderCol,0),MATCH("Range",Header,0))*INDEX(CarData,MATCH($H$19,HeaderCol,0),MATCH("Battery capacity",Header,0))*Parameters!$C$23 | L25: =(H25+I25)*(1+Parameters!$B$26)^-($A25-1) | M25: =(J25+K25)*(1+Parameters!$B$26)^-($A25-0.5) | O25: =VLOOKUP(INDEX(CarData,MATCH($N$19,HeaderCol,0),MATCH("Weight",Header,0)),TaxWeight,3,TRUE) | P25: =IF($A25>=Parameters!$B$27,INDEX(CarData,MATCH($N$19,HeaderCol,0),MATCH(P$6,Header,0)),0) | Q25: =Parameters!$B$10/INDEX(CarData,MATCH($N$19,HeaderCol,0),MATCH("Range",Header,0))*INDEX(CarData,MATCH($N$19,HeaderCol,0),MATCH("Battery capacity",Header,0))*Parameters!$C$23 | R25: =(N25+O25)*(1+Parameters!$B$26)^-($A25-1) | S25: =(P25+Q25)*(1+Parameters!$B$26)^-($A25-0.5)
A27: Price of Car | G27: =B21 | M27: =H21 | S27: =N21
A28: PV Total cost of ownership | G28: =SUM(F21:G25) | M28: =SUM(L21:M25) | S28: =SUM(R21:S25)
A29: Profit | G29: =INDEX(CarData,MATCH($B$19,HeaderCol,0),MATCH("Profit Margin",Header,0))*G27 | M29: =INDEX(CarData,MATCH($H$19,HeaderCol,0),MATCH("Profit Margin",Header,0))*M27 | S29: =INDEX(CarData,MATCH($N$19,HeaderCol,0),MATCH("Profit Margin",Header,0))*S27
A30: Manufacturing costs | G30: =G27-G29 | M30: =M27-M29 | S30: =S27-S29

Sheet Total profit-Weight
A1: Profit calculations
B3: Sales | C3: Profit | D3: Revenue | E3: Cost of Ownership | F3: Manufacturing costs
A4: Small Petrol | B4: =INDEX(Data!N:N,MATCH($A4,Data!A:A,0)) | C4: =$B4*'Calculations-Weight'!G15 | D4: =$B4*'Calculations-Weight'!G13 | E4: =$B4*'Calculations-Weight'!G14 | F4: =$B4*'Calculations-Weight'!$G16
A5: Medium Petrol | B5: =INDEX(Data!N:N,MATCH($A5,Data!A:A,0)) | C5: =$B5*'Calculations-Weight'!M15 | D5: =$B5*'Calculations-Weight'!M13 | E5: =$B5*'Calculations-Weight'!M14 | F5: =$B5*'Calculations-Weight'!$M16
A6: Large Petrol | B6: =INDEX(Data!N:N,MATCH($A6,Data!A:A,0)) | C6: =$B6*'Calculations-Weight'!S15 | D6: =$B6*'Calculations-Weight'!S13 | E6: =$B6*'Calculations-Weight'!S14 | F6: =$B6*'Calculations-Weight'!S16
A7: Small Electric | B7: =INDEX(Data!N:N,MATCH($A7,Data!A:A,0)) | C7: =$B7*'Calculations-Weight'!G29 | D7: =$B7*'Calculations-Weight'!G27 | E7: =$B7*'Calculations-Weight'!G28 | F7: =$B7*'Calculations-Weight'!$G30
A8: Medium Electric | B8: =INDEX(Data!N:N,MATCH($A8,Data!A:A,0)) | C8: =$B8*'Calculations-Weight'!M29 | D8: =$B8*'Calculations-Weight'!M27 | E8: =$B8*'Calculations-Weight'!M28 | F8: =$B8*'Calculations-Weight'!$M30
A9: Large Electric | B9: =INDEX(Data!N:N,MATCH($A9,Data!A:A,0)) | C9: =$B9*'Calculations-Weight'!S29 | D9: =$B9*'Calculations-Weight'!S27 | E9: =$B9*'Calculations-Weight'!S28 | F9: =$B9*'Calculations-Weight'!$S30
A11: Total | B11: =SUM(B4:B10) | C11: =SUM(C4:C10) | D11: =SUM(D4:D10) | E11: =SUM(E4:E10) | F11: =SUM(F4:F10)
A13: Check totals don't change: | B13: =IF(B11='Total profit-Base'!B11,"OK","Check") | C13: =IF(C11='Total profit-Base'!C11,"OK","Check") | D13: =IF(D11='Total profit-Base'!D11,"OK","Check") | F13: =IF(F11='Total profit-Base'!F11,"OK","Check")

Sheet Proposals
A1: Proposal calculations
A2: Adjustment factor A (Proposal 2): | B2: 0.97286052
A4: Proposal 1 (Price reduced by increase in cost of ownership)
A5: Model | B5: New Price | C5: New Profit Per Car | D5: New Profit Margin | E5: Expected Annual Profit | F5: New Cost of Ownership (per car)
A6: Small Petrol | B6: 27905.516 | C6: 878.01572 | D6: 0.031463877 | E6: 22448228 | F6: 36259.548
A7: Medium Petrol | B7: 36603.01 | C7: 2317.6305 | D7: 0.063318029 | E7: 4387274.5 | F7: 46370.486
A8: Large Petrol | B8: 64496.031 | C8: 6125.3814 | D8: 0.094972998 | E8: 11246200 | F8: 76248.72
A9: Small Electric | B9: 38875.688 | C9: 3751.838 | D9: 0.096508595 | E9: 41817987 | F9: 44114.071
A10: Medium Electric | B10: 45933.441 | C10: 4803.941 | D10: 0.10458483 | E10: 30221593 | F10: 53045.208
A11: Large Electric | B11: 64335.986 | C11: 7892.1065 | D11: 0.12267017 | E11: 30368826 | F11: 75065.809
A12: Total Expected Profit | B12: 1.4049011e+08
A14: Proposal 2 (Constant adjustment factor A)
A15: Model | B15: New Price | C15: New Profit Per Car | D15: New Profit Margin | E15: Expected Annual Profit | F15: New Cost of Ownership (per car)
A16: Small Petrol | B16: 27677.882 | C16: 650.38181 | D16: 0.023498251 | E16: 16628312 | F16: 36031.914
A17: Medium Petrol | B17: 35865.476 | C17: 1580.096 | D17: 0.044056182 | E17: 2991121.6 | F17: 45632.951
A18: Large Petrol | B18: 63805.057 | C18: 5434.4072 | D18: 0.085172046 | E18: 9977571.7 | F18: 75557.746
A19: Small Electric | B19: 38393.94 | C19: 3270.0904 | D19: 0.085172046 | E19: 36448428 | F19: 43632.323
A20: Medium Electric | B20: 46527.054 | C20: 5397.5544 | D20: 0.11600894 | E20: 33956015 | F20: 53638.822
A21: Large Electric | B21: 66965.881 | C21: 10522.001 | D21: 0.15712481 | E21: 40488660 | F21: 77695.704
A22: Total Expected Profit | B22: 1.4049011e+08
